Workbook

Sheet Servers
A1: Meta | F1: A. General | S1: B. Access / Pricing | Z1: C. Capabilities (summary; details on sheet "Capabilities") | AA1: D. Server-Side Logic | AD1: E. Aggregated Evaluation | AI1: F. Documentation Analysis | AM1: Meta
A2: Server | B2: Status | C2: Analyst / method | D2: Analysis date | E2: Fields filled, % | F2: Endpoint (from CSV) | G2: Documentation (from CSV) | H2: Addressing (from CSV) | I2: Code repository link | J2: Documentation used (link) | K2: Open code = deployed server? | L2: MCP version (protocol) | M2: Commit hash | N2: Commit date | O2: Implementation language | P2: MCP SDK and version | Q2: Code public? | R2: License | S2: MCP server access: free / paid | T2: MCP server cost (how much) | U2: Linked software: open source / paid | V2: Linked software cost | W2: Pricing model (details) | X2: Other access restrictions (which) | Y2: Restrictions controlled by | Z2: Capabilities implemented (count) | AA2: Additional logic between LLM and software (governance) | AB2: Server structure | AC2: Structure: explanation | AD2: Number of actions (from sheet Actions) | AE2: Number of actions (manual / comment) | AF2: Tokens before first action | AG2: Token counting method | AH2: Actions a human can do but the agent cannot | AI2: Recommendations in docs not enforced by the server | AJ2: Governance promises (data, rights, reversibility, logging) | AK2: Promises to the user | AL2: Promises vs. server logic | AM2: Sources (links) | AN2: Notes / questions
A3: tavily | B3: Verified | C3: Manual analysis using Claude Opus 5.5 for verification and code analysis | D3: 2026-10-12; re-analysed 2026-10-15 (new commit in the repository) | E3: =((LEN(TRIM(I3))>0)*1+(LEN(TRIM(J3))>0)*1+(LEN(TRIM(K3))>0)*1+(LEN(TRIM(L3))>0)*1+(LEN(TRIM(M3))>0)*1+(LEN(TRIM(N3))>0)*1+(LEN(TRIM(O3))>0)*1+(LEN(TRIM(P3))>0)*1+(LEN(TRIM(Q3))>0)*1+(LEN(TRIM(R3))>0)*1+(LEN(TRIM(S3))>0)*1+(LEN(TRIM(T3))>0)*1+(LEN(TRIM(U3))>0)*1+(LEN(TRIM(V3))>0)*1+(LEN(TRIM(W3))>0)*1+(LEN(TRIM(X3))>0)*1+(LEN(TRIM(Y3))>0)*1+(LEN(TRIM(AA3))>0)*1+(LEN(TRIM(AB3))>0)*1+(LEN(TRIM(AC3))>0)*1+(LEN(TRIM(AE3))>0)*1+(LEN(TRIM(AF3))>0)*1+(LEN(TRIM(AG3))>0)*1+(LEN(TRIM(AH3))>0)*1+(LEN(TRIM(AI3))>0)*1+(LEN(TRIM(AJ3))>0)*1+(LEN(TRIM(AK3))>0)*1+(LEN(TRIM(AL3))>0)*1)/28 | F3: https://mcp.tavily.com/mcp | G3: https://docs.tavily.com/mcp | H3: global | I3: https://github.com/tavily-ai/tavily-mcp (local stdio version only; the remote server's code is not published) | J3: https://docs.tavily.com/documentation/mcp (the CSV link https://docs.tavily.com/mcp now serves the documentation MCP server, not a page) | K3: Partially | L3: SDK supports 2025-11-25 (latest), 2025-06-18, 2025-03-26, 2024-11-05, 2024-10-07; not 2026-07-28 | M3: 688b0f78d518d507cb31b94d9cc0e44c6eadd7c0 | N3: 2026-10-15 | O3: TypeScript (Node.js >= 20) | P3: @modelcontextprotocol/sdk 1.31.0 (low-level Server class) | Q3: Partially | R3: MIT (local version only) | S3: Freemium | T3: The MCP server itself is free (MIT code); you pay for the Tavily API calls it makes | U3: Paid | V3: Free: 1,000 credits/month; PAYG $0.008/credit; Project 4,000 cr./$30; Bootstrap 15,000/$100; Startup 38,000/$220; Growth 100,000/$500; Enterprise custom | W3: Credits. Search: basic/fast/ultra-fast = 1 credit, advanced = 2. Extract: 1 credit per 5 successful URLs (advanced 2). Map: 1 credit per 10 pages (with instructions 2). Crawl = Map + Extract. Research: mini 4-110, pro 15-250 credits per request. | X3: Keyless mode (no key): free, rate-limited, only Search and Extract; Crawl/Map/Research need a key. Rate limits: development key 100 req/min, production key 1,000/min; Crawl 100/min; Research 20/min. Production key only with a paid plan or PAYGO. With OAuth the key `mcp_auth_default` is used (personal before team), else `default`, else the first one. | Y3: Tavily (API side); the MCP server adds only research timeouts | Z3: =COUNTIFS(Capabilities!$A:$A,$A3,Capabilities!$C:$C,"Yes")+COUNTIFS(Capabilities!$A:$A,$A3,Capabilities!$C:$C,"Partially") | AA3: 1) DEFAULT_PARAMETERS set by the operator REPLACE the AI's search parameters (not only fill gaps), silently. 2) Parameter correction: country forces topic=general; dates remove time_range; empty values removed. 3) crawl hard-codes chunks_per_source=3. 4) crawl output truncated to the first 200 characters per page. 5) research: polling 2 s x1.5 up to 10 s, limit 5/15 min, automatic switch to streaming; incomplete report -> error. 6) X-Session-Id / X-Human-Id / X-Client-Source headers on every request (vendor analytics). 7) tavily_feedback tool instructs the agent to rate every result and send its final answer to Tavily. 8) Keyless limit responses return commercial options (x402 payment, sign-up, bonus credits for answering questions) as normal text. No permission checks, human confirmation or domain restrictions. | AB3: Standard | AC3: Flat: one process -> 6 tools, each a wrapper around one REST endpoint of api.tavily.com. No hierarchy, no sub-servers. | AD3: =COUNTIF(Actions!$A:$A,$A3) | AE3: 6 in the local code; 5 in the remote server documentation (without tavily_feedback) | AF3: ~3,300 | AG3: Length of the JSON tool descriptions / 4 characters per token (+-30 %, model-dependent); no server instructions | AH3: Search API parameters not exposed: include_answer, auto_parameters, chunks_per_source, include_domains_mode, language, filter_by_language, include_published_date, filter_by_published_date, include_usage, safe_search. Cannot change chunks_per_source in crawl (fixed 3). Cannot view credit usage, manage keys, plan or team (web dashboard only). Cannot get the full page text in crawl (only 200 characters). | AI3: Use an opaque user ID, not an e-mail ("prefer opaque identifiers ... over raw PII"). The official OpenAI example sets "require_approval": "never" (human confirmation off). The API key is suggested in the URL (?tavilyApiKey=...) without a risk warning. No recommendations on human confirmation. | AJ3: Human ID hashed with SHA-256 before storage, raw ID not stored. Privacy policy: Tavily may use parts of request data to improve future responses (legitimate interest; EU users can object by e-mail); queries may be passed to third-party search indexes (e.g. Google); data kept while the account exists; deletion on request. Nothing on logging of agent actions or reversibility. | AK3: "real-time web search", "seamless experience without requiring local installation"; identifiers help Tavily "better understand multi-step interactions and improve response quality" | AL3: Hashing of the human ID cannot be verified from the code (API side). The server forwards X-Human-Id only if it is set (consistent). | AM3: https://github.com/tavily-ai/tavily-mcp/tree/688b0f78d518d507cb31b94d9cc0e44c6eadd7c0 https://docs.tavily.com/documentation/mcp https://docs.tavily.com/documentation/api-credits https://docs.tavily.com/documentation/rate-limits https://docs.tavily.com/documentation/keyless https://docs.tavily.com/documentation/api-reference/endpoint/search https://www.tavily.com/privacy | AN3: The CSV endpoint is the remote server (closed code); the code analysis refers to the local version. Package version 0.2.23 in package.json, but the server reports 0.2.22. Last change to the server code: 08dfecd (2026-10-15).
A4: grafana | B4: Verified | C4: Manual analysis using Claude Opus 5.5 for verification and code analysis | D4: 2026-10-12; re-analysed 2026-10-23 (new commit in the repository) | E4: =((LEN(TRIM(I4))>0)*1+(LEN(TRIM(J4))>0)*1+(LEN(TRIM(K4))>0)*1+(LEN(TRIM(L4))>0)*1+(LEN(TRIM(M4))>0)*1+(LEN(TRIM(N4))>0)*1+(LEN(TRIM(O4))>0)*1+(LEN(TRIM(P4))>0)*1+(LEN(TRIM(Q4))>0)*1+(LEN(TRIM(R4))>0)*1+(LEN(TRIM(S4))>0)*1+(LEN(TRIM(T4))>0)*1+(LEN(TRIM(U4))>0)*1+(LEN(TRIM(V4))>0)*1+(LEN(TRIM(W4))>0)*1+(LEN(TRIM(X4))>0)*1+(LEN(TRIM(Y4))>0)*1+(LEN(TRIM(AA4))>0)*1+(LEN(TRIM(AB4))>0)*1+(LEN(TRIM(AC4))>0)*1+(LEN(TRIM(AE4))>0)*1+(LEN(TRIM(AF4))>0)*1+(LEN(TRIM(AG4))>0)*1+(LEN(TRIM(AH4))>0)*1+(LEN(TRIM(AI4))>0)*1+(LEN(TRIM(AJ4))>0)*1+(LEN(TRIM(AK4))>0)*1+(LEN(TRIM(AL4))>0)*1)/28 | F4: https://mcp.grafana.com/mcp | G4: https://grafana.com/docs/grafana/latest/developer-resources/mcp/ | H4: global | I4: https://github.com/grafana/mcp-grafana (open server; the cloud server at the CSV endpoint is not fully published) | J4: https://grafana.com/docs/grafana/latest/developer-resources/mcp/ (open server, from CSV); https://grafana.com/docs/grafana-cloud/ai-tools/mcp-servers/cloud-mcp/ (cloud server) | K4: Partially | L4: go-sdk v1.8.0 supports 2026-07-28 (latest, default), 2025-11-25, 2025-06-18, 2025-03-26, 2024-11-05 | M4: e97cd4479eb40d25bc8d466db1651c29ce0c783e | N4: 2026-10-23 | O4: Go (module github.com/grafana/mcp-grafana/v2, go 1.26.10) | P4: github.com/modelcontextprotocol/go-sdk v1.8.0 (official) | Q4: Partially | R4: Apache 2.0 (open server); cloud server closed | S4: Freemium | T4: Open server free. Cloud: each connected user counts as an "active AI user" of Grafana Assistant. Free plan: up to 3 active AI users/month (40M tokens each) + 25M tokens for service accounts, blocked above the limit. Pro: $20 per active AI user (40M tokens included), extra tokens $2 per 1M. Simple data queries consume no tokens, Assistant functions do. | U4: Open source + paid cloud | V4: Grafana OSS free; Grafana Cloud Free $0, Pro from $19/month + usage, Enterprise from $25,000/year | W4: Cloud MCP is billed via Grafana Assistant (active AI users + tokens); see server cost. Grafana Cloud itself: usage-based tiers. | X4: Grafana >= 9.0. Cloud: Grafana Cloud only, Assistant available on the stack, Assistant terms accepted; role "Assistant Cloud MCP User" (Editor+ by default); Write may need "Assistant Admin"; OAuth consent screen with Read / Query / Write levels (Write needs scope grafana:write). Rate limits not documented; default request timeout to Grafana 10 s. | Y4: Grafana administrator (RBAC), server operator (flags --enabled-tools, --disable-write, --disable-query ...), user (cloud OAuth consent screen) | Z4: =COUNTIFS(Capabilities!$A:$A,$A4,Capabilities!$C:$C,"Yes")+COUNTIFS(Capabilities!$A:$A,$A4,Capabilities!$C:$C,"Partially") | AA4: 1) Operator modes: --disable-write (removes writing tools; grafana_api_request GET-only), --disable-query, category toggles (12 categories off by default). 2) The server classifies query languages by danger (SQL and InfluxQL count as writing). 3) Server instructions change with the configuration. 4) Unknown arguments rejected with a list of valid names; automatic type coercion. 5) Loki cost limiter (--loki-guardrail-mode off|shadow|enforce: selector, 24 h range, 100 GiB scan; rejects with a rewrite hint; off by default). 6) Enforced Loki matchers (the AI can only narrow; fail closed; warns about bypasses). 7) Response size limits (Loki 10 lines default, max 100, +1 line to signal truncation); economical dashboard tools. 8) HTTP security: Host/Origin checks, no cross-domain redirects, URL whitelist. 9) Required RBAC permissions declared in _meta, checked by Grafana (403). 10) Metrics/tracing; arguments in spans only with a flag. No human confirmation (cloud: only the OAuth consent screen). | AB4: Standard | AC4: Flat but modular: 34 categories switched on/off by flags; no hierarchy of sub-servers. Cloud: Tempo tools are proxied from the MCP servers of Tempo data sources. A universal tool (grafana_api_request) covers the whole Grafana API. | AD4: =COUNTIF(Actions!$A:$A,$A4) | AE4: 119 tools in the open code, 79 enabled by default; several are multi-operation; grafana_api_request reaches any API endpoint. Cloud server: list in the docs incomplete (by category), without grafana_api_request, plus Assistant tools. | AF4: ~27,000 by default (79 tools ~26,600 + instructions ~460); ~40,000 with everything enabled | AG4: Length of the reconstructed tools/list JSON / 4 characters per token (+-30 %) | AH4: With grafana_api_request (default): almost nothing beyond the token's RBAC rights; the real boundary is RBAC. Without it (or in the cloud server): no tools to delete dashboards, folders or data sources, to manage users, teams, service accounts and roles (admin tools read only), organisation settings, remove/disable plugins, change resource permissions. Browser-only: visual panel editing, Explore UI (agent can only get a deeplink or a panel image). | AI4: Give the service account only the necessary permissions (Editor is "less restrictive"). Use --include-args-in-spans only outside production / without personal data. Do not expose the server without --server-auth-token; use TLS. For URL overrides deploy behind an authenticating proxy and restrict outbound network access. Disable bypasses (--disable-api, --disable-rendering, --disable-assistant) for Loki restrictions to work. Cloud: for read-only untick both Write and Query ("clearing only Write access still allows raw SQL"). No recommendations on human confirmation. | AJ4: Anonymous usage statistics ON by default (every 4 h: tools called, error counts, configuration; not arguments, queries, logs, credentials, instance URL; coarse region/network added from IP; opt-out --usage-stats=disabled or DO_NOT_TRACK=1). SQL: "credentials are never seen by the MCP server". Cloud: "Grafana doesn't train AI models on your PromQL, LogQL queries, investigation content, or prompt payload data"; LLM providers (Anthropic, Google Vertex AI, Amazon Bedrock) with zero retention; conversations kept 30/90/180 days (default 90); up to 30 days after deletion; employee access restricted and audited. Reversibility: dashboard versions exist, no one-command rollback; delete_annotation is "Permanently delete". | AK4: Feature list "for informational purposes only and does not represent a roadmap or commitment"; deeplinks "instead of relying on LLM URL guessing" | AL4: Statistics statements match the code (usagestats/), but on-by-default means data is sent without explicit consent. Loki restrictions are implemented and honestly documented together with their bypasses. | AM4: https://github.com/grafana/mcp-grafana/tree/e97cd4479eb40d25bc8d466db1651c29ce0c783e https://grafana.com/docs/grafana/latest/developer-resources/mcp/ https://grafana.com/docs/grafana-cloud/ai-tools/mcp-servers/cloud-mcp/ https://grafana.com/docs/grafana-cloud/ai-tools/mcp-servers/register-oauth-client https://grafana.com/pricing/ https://grafana.com/docs/grafana-cloud/platform/pricing-and-usage/assistant/ https://grafana.com/docs/grafana-cloud/platform/grafana-assistant/privacy-and-security/privacy/ https://grafana.com/docs/grafana/latest/developer-resources/mcp/anonymous-usage-statistics/ https://grafana.com/docs/grafana/latest/developer-resources/api-reference/http-api/ | AN4: The CSV endpoint is the cloud server (separate hosted product, not fully published); the code analysis refers to the open server. Latest release tag v2.1.1. Actions sheet: tool list generated from the appendix 02b (type from readOnlyHint of all variants; description = first sentence of the verbatim description).
A5: basic-memory | B5: Verified | C5: Manual analysis using Claude Opus 5.5 for verification and code analysis | D5: 2026-10-12; re-analysed 2026-10-23 (new commit in the repository) | E5: =((LEN(TRIM(I5))>0)*1+(LEN(TRIM(J5))>0)*1+(LEN(TRIM(K5))>0)*1+(LEN(TRIM(L5))>0)*1+(LEN(TRIM(M5))>0)*1+(LEN(TRIM(N5))>0)*1+(LEN(TRIM(O5))>0)*1+(LEN(TRIM(P5))>0)*1+(LEN(TRIM(Q5))>0)*1+(LEN(TRIM(R5))>0)*1+(LEN(TRIM(S5))>0)*1+(LEN(TRIM(T5))>0)*1+(LEN(TRIM(U5))>0)*1+(LEN(TRIM(V5))>0)*1+(LEN(TRIM(W5))>0)*1+(LEN(TRIM(X5))>0)*1+(LEN(TRIM(Y5))>0)*1+(LEN(TRIM(AA5))>0)*1+(LEN(TRIM(AB5))>0)*1+(LEN(TRIM(AC5))>0)*1+(LEN(TRIM(AE5))>0)*1+(LEN(TRIM(AF5))>0)*1+(LEN(TRIM(AG5))>0)*1+(LEN(TRIM(AH5))>0)*1+(LEN(TRIM(AI5))>0)*1+(LEN(TRIM(AJ5))>0)*1+(LEN(TRIM(AK5))>0)*1+(LEN(TRIM(AL5))>0)*1)/28 | F5: https://cloud.basicmemory.com/mcp | G5: https://docs.basicmemory.com/cloud/cloud-guide | H5: global | I5: https://github.com/basicmachines-co/basic-memory | J5: https://docs.basicmemory.com/cloud/cloud-guide (from CSV); https://docs.basicmemory.com/reference/mcp-tools-reference | K5: Partially | L5: Python SDK mcp 2.3.0: 2024-11-05, 2025-03-26, 2025-06-18, 2025-11-25 (initialize handshake) and 2026-07-28 (stateless); latest 2026-07-28 | M5: 9b47a7cd4784ca3a4df5d85437bdbd2db2dee587 | N5: 2026-10-23 | O5: Python >= 3.12 | P5: FastMCP 4.1.3 (on top of the official mcp 2.3.0) | Q5: Partially | R5: AGPL-3.0 (cloud parts partly closed) | S5: Freemium | T5: Local: free ("Free to run locally"). Cloud: active subscription required. Team $15 per seat/month ($13 from 10 seats, $12 from 20); Business $30 per seat/month; Agent Infrastructure custom; 7-day trial. | U5: Open source + paid cloud | V5: Program open source (AGPL-3.0); cloud subscription as above (README still describes the old "$15.00/mo ... One plan, no tiers" with OSS discount code BMFOSS) | W5: Per seat per month (Team / Business), Agent Infrastructure: credits / metered usage. Cloud built on WorkOS AuthKit, Neon Postgres, Tigris S3, Polar.sh. | X5: Cloud: subscription ("Active subscription required"). User settings in ~/.basic-memory/config.json: project deletion off by default (enable_project_delete=false), POSIX tools can be hidden, overwriting notes forbidden by default. Cloud: ZIP upload up to 100 MB; .env and similar files are not uploaded. | Y5: Basic Machines (subscription); user (local config) | Z5: =COUNTIFS(Capabilities!$A:$A,$A5,Capabilities!$C:$C,"Yes")+COUNTIFS(Capabilities!$A:$A,$A5,Capabilities!$C:$C,"Partially") | AA5: 1) Behaviour rules only in server instructions (check recent_activity before answering; offer to save and wait for agreement; "Do not create notes unprompted") - not enforced by code. 2) Overwrite protection: ALREADY_EXISTS unless overwrite=true. 3) Optimistic locking with expected_checksum (REVISION_CONFLICT). 4) Dangerous operations need explicit parameters: recursive=true for folder deletion; project deletion hidden unless enable_project_delete. 5) Project boundaries incl. symlinks (OUTSIDE_PROJECT). 6) Memory: past writes come back in future sessions; similar-notes hints after writing. 7) Built-in manual for the AI (memory://man). 8) Client-specific behaviour (search/fetch only for OpenAI). 9) Silent auto-update of CLI installs every 24 h. No permission checks locally, no protocol-level human confirmation, no rate limits. | AB5: Standard | AC5: Flat, one server; tool groups switched by FastMCP tags; transition period with old and new (bm_*) sets visible at the same time; local <-> cloud routing by project/workspace. | AD5: =COUNTIF(Actions!$A:$A,$A5) | AE5: 37 visible by default (39 registered, 2 project-deletion tools hidden; 2 more defined but not registered); about 15 actions that differ in meaning (old/new duplicates, OpenAI wrappers). Several tools contain multiple operations (bm_edit 7 commands, bm_project list/create/recent). | AF5: ~11,400 (tools + resources + prompts ~10,900, instructions ~520) | AG5: Length of the reconstructed description / 4 characters per token (+-30 %); about half is duplicate old tools | AH5: Import from ChatGPT, Claude, documents, memory.json (CLI only). Cloud: snapshots and restore, push/pull sync (bisync), ZIP upload, sharing, subscription, teams and workspaces (except list_workspaces). Database maintenance: reindex, prune, orphans, doctor, update. Delete a project unless the user enabled it. Cloud web app: comments and suggested edits (partly via review_note in the cloud MCP). | AI5: "Deletion is irreversible for active project storage"; "Back up any local files you need before running the destructive command". Agents should not write CriticMarkup directly. Pass workspace for a clean deletion of cloud data from a local session. No separate confirmation step before destructive actions is described. | AJ5: Local: "Notes and content never leave your device". Cloud: "We don't train AI models", encrypted at rest and in transit, servers in the USA, data kept 30 days after cancellation (backups up to 90 days), "We don't sell your data". CLI telemetry on by default (anonymous CLI -> cloud funnel events to Umami Cloud; no file contents, titles, IP, tool calls; opt-out BASIC_MEMORY_NO_PROMOS=1); Logfire off by default. Reversibility: "No lock-in ... Export to local Markdown any time"; cloud snapshots and point-in-time restore; no versions for local notes. Diagnostics read-only, secrets masked. | AK5: "Your AI never forgets again"; "Every tool is annotated with MCP behavior hints ... so agents can pick the right one without trial-and-error"; "Cancel anytime, your data stays yours" | AL5: Annotation promise kept (all tools annotated). "Do not create notes unprompted" exists only as text in the instructions; the code does not enforce it. "Notes never leave your device" consistent with the code when the cloud is off; CLI telemetry sends events only (analytics.py). | AM5: https://github.com/basicmachines-co/basic-memory/tree/9b47a7cd4784ca3a4df5d85437bdbd2db2dee587 https://docs.basicmemory.com/cloud/cloud-guide https://docs.basicmemory.com/reference/mcp-tools-reference https://docs.basicmemory.com/cloud/routing https://basicmemory.com/pricing https://basicmemory.com/privacy | AN5: The CSV endpoint is the cloud server; it has closed extras (review_note, open_basic_memory, review_mode, workspace). The code analysis refers to the open server. Actions sheet: generated from the appendix 03b (type from readOnlyHint; description = first sentence of the verbatim description).
A6: shapes | B6: Verified | C6: Manual analysis using Claude Opus 5.5 for verification and code analysis | D6: 2026-10-12 | E6: =((LEN(TRIM(I6))>0)*1+(LEN(TRIM(J6))>0)*1+(LEN(TRIM(K6))>0)*1+(LEN(TRIM(L6))>0)*1+(LEN(TRIM(M6))>0)*1+(LEN(TRIM(N6))>0)*1+(LEN(TRIM(O6))>0)*1+(LEN(TRIM(P6))>0)*1+(LEN(TRIM(Q6))>0)*1+(LEN(TRIM(R6))>0)*1+(LEN(TRIM(S6))>0)*1+(LEN(TRIM(T6))>0)*1+(LEN(TRIM(U6))>0)*1+(LEN(TRIM(V6))>0)*1+(LEN(TRIM(W6))>0)*1+(LEN(TRIM(X6))>0)*1+(LEN(TRIM(Y6))>0)*1+(LEN(TRIM(AA6))>0)*1+(LEN(TRIM(AB6))>0)*1+(LEN(TRIM(AC6))>0)*1+(LEN(TRIM(AE6))>0)*1+(LEN(TRIM(AF6))>0)*1+(LEN(TRIM(AG6))>0)*1+(LEN(TRIM(AH6))>0)*1+(LEN(TRIM(AI6))>0)*1+(LEN(TRIM(AJ6))>0)*1+(LEN(TRIM(AK6))>0)*1+(LEN(TRIM(AL6))>0)*1)/28 | F6: https://mcp.shapes.co/mcp | G6: https://shapes.co/mcp | H6: global | I6: Not published | J6: https://shapes.co/mcp (from CSV); https://mcp.shapes.co/ (technical page); https://claude.com/connectors/shapes | K6: Unknown | L6: Not published (requires sign-in) | M6: Not applicable (closed code) | N6: Documentation snapshot 2026-10-12 | O6: Not published | P6: Not published | Q6: No | R6: Proprietary | S6: Paid | T6: No separate price; only for existing Shapes customers ("Existing Shapes customers can connect directly"), others contact sales | U6: Paid | V6: Core $8 per seat/month, Plus $12 per seat/month (billed annually), minimum subscription (size not given); Surveys, Performance and Compensation modules priced on request | W6: Per-seat SaaS subscription; MCP not mentioned in the plan feature lists | X6: OAuth sign-in with each employee's own Shapes account; "Your existing Shapes permissions carry through to every Claude conversation"; the Claude connector is set up by the organisation's administrator. Rate limits not documented. | Y6: Customer's Shapes HR administrators (permissions); Shapes (subscription) | Z6: =COUNTIFS(Capabilities!$A:$A,$A6,Capabilities!$C:$C,"Yes")+COUNTIFS(Capabilities!$A:$A,$A6,Capabilities!$C:$C,"Partially") | AA6: According to the documentation (not verifiable): 1) Read-only at the level of the whole server - no writing tools at all. 2) User permissions carry over ("you can only access data you're authorized to see"), filtering on the Shapes side. 3) Aggregating tools compute statistics instead of returning raw records. 4) Separate "my" tools for the user's own data. Human confirmation, confidence scores, logging not described. | AB6: Standard | AC6: Flat set of tools (according to the documentation) | AD6: =COUNTIF(Actions!$A:$A,$A6) | AE6: 35 according to mcp.shapes.co ("35+ tools"), all read-only | AF6: Cannot be determined | AG6: Tool descriptions not published | AH6: Any changes: create or change an employee, book time off, answer a survey, carry out a review, upload or sign a document (Docs & eSign). Compensation: promised "compensation gaps" analysis but no salary tool in the list (possibly via employee fields - unconfirmed). Shapes AI functions (Vibe Views, Shapes Agents, Workflows). | AI6: None explicit; no recommendations on human confirmation (not needed, read-only) or on handling personal data in an AI chat. | AJ6: "Shapes is SOC2 certified and GDPR compliant so your people data stays protected, always"; "Your permissions carry over" / "No one sees more than they should". Privacy policy: AI features may use unnamed third-party LLM providers; data stored in Israel, EEA, UK, USA etc.; Shapes may train models on product usage data after removing personal data; customer data governed by a DPA and the "AI Modules Schedule". HR data received by the AI client goes to the AI provider - not mentioned in the MCP documentation. | AK6: "Connect in minutes. No engineering required."; the AI can answer about "attrition risk, headcount, and compensation gaps" | AL6: Read-only confirmed by the tool names (only list_, get_, aggregate_, search_, read_). Compensation analysis not confirmed by the tool list. | AM6: https://shapes.co/mcp https://mcp.shapes.co/ https://mcp.shapes.co/.well-known/oauth-protected-resource https://mcp.shapes.co/.well-known/oauth-authorization-server https://shapes.co/pricing https://shapes.co/privacy-policy https://claude.com/connectors/shapes https://getknit.dev/mcp-servers/shapes | AN6: Closed code, server returns 401 without sign-in, so tools/list is unavailable. The landing page gives http:// instead of https:// (probably a typo). Company: DreamTeam HR Apps Ltd. (d/b/a Shapes). Not to be confused with the third-party Knit wrapper with 25 writing actions.
A7: lucid | B7: Verified | C7: Manual analysis using Claude Opus 5.5 for verification and code analysis | D7: 2026-10-13; re-analysed 2026-10-22 (new commit in the repository) | E7: =((LEN(TRIM(I7))>0)*1+(LEN(TRIM(J7))>0)*1+(LEN(TRIM(K7))>0)*1+(LEN(TRIM(L7))>0)*1+(LEN(TRIM(M7))>0)*1+(LEN(TRIM(N7))>0)*1+(LEN(TRIM(O7))>0)*1+(LEN(TRIM(P7))>0)*1+(LEN(TRIM(Q7))>0)*1+(LEN(TRIM(R7))>0)*1+(LEN(TRIM(S7))>0)*1+(LEN(TRIM(T7))>0)*1+(LEN(TRIM(U7))>0)*1+(LEN(TRIM(V7))>0)*1+(LEN(TRIM(W7))>0)*1+(LEN(TRIM(X7))>0)*1+(LEN(TRIM(Y7))>0)*1+(LEN(TRIM(AA7))>0)*1+(LEN(TRIM(AB7))>0)*1+(LEN(TRIM(AC7))>0)*1+(LEN(TRIM(AE7))>0)*1+(LEN(TRIM(AF7))>0)*1+(LEN(TRIM(AG7))>0)*1+(LEN(TRIM(AH7))>0)*1+(LEN(TRIM(AI7))>0)*1+(LEN(TRIM(AJ7))>0)*1+(LEN(TRIM(AK7))>0)*1+(LEN(TRIM(AL7))>0)*1)/28 | F7: https://mcp.lucid.app/mcp | G7: https://github.com/lucidsoftware/lucid-mcp-server | H7: global | I7: https://github.com/lucidsoftware/lucid-mcp-server (skills and plugins only; the server code is closed) | J7: https://help.lucid.co/hc/en-us/articles/42578801807508-Integrate-Lucid-with-AI-tools-using-the-Lucid-MCP-server; https://community.lucid.co/product-questions-3/available-actions-with-the-lucid-mcp-server-13985; https://lucid.co/mcp-server | K7: No | L7: Not published | M7: f3827e4cd2d449463350cd0d725e35d6d2ecd082 (skills repository; server code not applicable) | N7: 2026-10-22 | O7: Not published | P7: Not published | Q7: No | R7: Server proprietary; skills/plugins repository MIT (c) 2026 Lucid Software, Inc. | S7: Freemium | T7: No separate fee; available on Free, Individual, Team and Enterprise plans, not for FedRAMP accounts | U7: Freemium | V7: Lucidchart/Lucidspark proprietary SaaS with a free plan; exact prices could not be checked (pricing page needs JavaScript; manual check: https://lucid.app/pricing/lucidchart) | W7: Plan-based SaaS; API key access for Team/Enterprise marked as premium | X7: Team/Enterprise: the administrator must enable MCP (Admin -> Security -> Feature controls / AI controls -> MCP access); enabling allows any AI client (cannot be limited to specific clients). The server sees all documents the user can access in their account, not other accounts. Reduced endpoints /readonly and /repositories. Not for FedRAMP. | Y7: Lucid account administrator; Lucid (plans, FedRAMP); user (choice of endpoint) | Z7: =COUNTIFS(Capabilities!$A:$A,$A7,Capabilities!$C:$C,"Yes")+COUNTIFS(Capabilities!$A:$A,$A7,Capabilities!$C:$C,"Partially") | AA7: 1) Different endpoints = different rights (/mcp/readonly, /mcp/repositories) instead of scopes. 2) Validation before action (lucid_validate_diagram_specification; creation tools require reading a reference resource first). 3) lucid_run_script: "Changes are atomic and time-limited". 4) lucid_submit_feedback sends feedback to Airfocus with user ID, account ID and client user agent. 5) Behaviour rules moved to skills outside the server ("Confirm before destructive actions, bulk changes, broad permission changes, or anonymous share links") - not enforced by the server. 6) Skill "visualizations" promotes Lucid over Mermaid/ASCII/Markdown tables. 7) Pass-through: no storage of documents, prompts or queries. | AB7: Non-standard | AC7: One service via three endpoints with different tool sets (full / read-only / repositories only), plus a separate layer of skills/plugins distributed outside the server. | AD7: =COUNTIF(Actions!$A:$A,$A7) | AE7: 35 in Composio (2026-10-12), 30 in Scalekit; combined list 40 names; only lucid_submit_feedback officially confirmed. The set changes over time. | AF7: Cannot be determined | AG7: Descriptions not published; catalogues call them "long" with "detailed usage rules" | AH7: Create data-linked diagrams that update automatically; export to Visio (PNG only); create diagrams from templates, delete tabs (unconfirmed); access documents outside the own account; administer the account and user rights. | AI7: Skill lucid: confirm deletion, bulk changes, permission changes and anonymous links; read the document before editing; do not invent IDs (instructions for the AI, not server checks). The Help Center gives no recommendations on human review. The API key is advertised for working without confirmations ("no runtime approval prompt"). | AJ7: "The server acts as a pass-through - it does not retain document content, user prompts, or queries. Your credentials are never shared outside your Lucid account"; "It cannot access documents owned or created by users outside your account"; feedback goes to Airfocus with user/account ID "only when the feedback tool is called"; AI clients are "Non-Lucid Applications" governed by the AI provider contract. | AK7: "Connect your AI tools to Lucid to intelligently search for files, create visuals, and share with your team"; "compatible with any MCP client"; the action list in the community post is called "exhaustive" | AL7: "Pass-through" cannot be verified (closed code). The read-only endpoint is described, but its exact tool set is not named. | AM7: https://github.com/lucidsoftware/lucid-mcp-server/tree/f3827e4cd2d449463350cd0d725e35d6d2ecd082 https://help.lucid.co/hc/en-us/articles/42578801807508-Integrate-Lucid-with-AI-tools-using-the-Lucid-MCP-server https://community.lucid.co/product-questions-3/available-actions-with-the-lucid-mcp-server-13985 https://composio.dev/toolkits/lucid_mcp/framework/hermes-agent.md https://www.scalekit.com/connectors/lucidmcp | AN7: The CSV link points to a repository without server code (skills and plugin configs only). Tool names come from two third-party catalogues whose lists differ (35 vs 30). OAuth metadata could not be checked (robots.txt).
A8: gocardless | B8: Verified | C8: Manual analysis using Claude Opus 5.5 for verification and code analysis | D8: 2026-10-13 | E8: =((LEN(TRIM(I8))>0)*1+(LEN(TRIM(J8))>0)*1+(LEN(TRIM(K8))>0)*1+(LEN(TRIM(L8))>0)*1+(LEN(TRIM(M8))>0)*1+(LEN(TRIM(N8))>0)*1+(LEN(TRIM(O8))>0)*1+(LEN(TRIM(P8))>0)*1+(LEN(TRIM(Q8))>0)*1+(LEN(TRIM(R8))>0)*1+(LEN(TRIM(S8))>0)*1+(LEN(TRIM(T8))>0)*1+(LEN(TRIM(U8))>0)*1+(LEN(TRIM(V8))>0)*1+(LEN(TRIM(W8))>0)*1+(LEN(TRIM(X8))>0)*1+(LEN(TRIM(Y8))>0)*1+(LEN(TRIM(AA8))>0)*1+(LEN(TRIM(AB8))>0)*1+(LEN(TRIM(AC8))>0)*1+(LEN(TRIM(AE8))>0)*1+(LEN(TRIM(AF8))>0)*1+(LEN(TRIM(AG8))>0)*1+(LEN(TRIM(AH8))>0)*1+(LEN(TRIM(AI8))>0)*1+(LEN(TRIM(AJ8))>0)*1+(LEN(TRIM(AK8))>0)*1+(LEN(TRIM(AL8))>0)*1)/28 | F8: https://mcp.gocardless.com/mcp | G8: https://developer.gocardless.com/developer-tools/mcp/ | H8: global | I8: Not published | J8: https://docs.gocardless.com/docs/developer-resources/mcp (CSV link redirects here); https://support.gocardless.com/hc/en-gb/articles/26830050176028-Use-AI-to-manage-your-account | K8: Unknown | L8: Not published | M8: Not applicable (closed code) | N8: Documentation snapshot 2026-10-13 | O8: Not published | P8: Not published | Q8: No | R8: Proprietary | S8: Free | T8: "The CLI, MCP and MCP Data are provided free of charge", but "GoCardless reserves the right to charge in the future" (terms 2.3) | U8: Paid | V8: Per transaction: Standard 1% + 20p (max £4), international 2% + 20p; Advanced 1.25% + 20p (max £5); Pro 1.4% + 20p (max £5.60); Custom by agreement; no subscription fee except add-ons (£50 and £150/month) | W8: Transaction fees for the payment service; MCP free | X8: Claude requires Pro, Max, Team or Enterprise (free AI plans "typically don't support MCPs"); on Team/Enterprise the Owner adds the connector first. Rights chosen by the user at sign-in (everything, read-only or specific actions); intersected with the user's dashboard role; bulk limits (e.g. max 25 payments at a time); access expires periodically. Live and Sandbox are separate connections. Rate limits not documented. | Y8: User (rights at sign-in), dashboard administrator (roles), GoCardless (limits, masking) | Z8: =COUNTIFS(Capabilities!$A:$A,$A8,Capabilities!$C:$C,"Yes")+COUNTIFS(Capabilities!$A:$A,$A8,Capabilities!$C:$C,"Partially") | AA8: According to the documentation (closed code): 1) Money-moving actions need explicit confirmation after a preview (mechanism not disclosed). 2) Masking of e-mail, phone, postcode, ID numbers before the AI sees them; bank details never passed. 3) Granular rights at sign-in (down to "refunds only") intersected with the user role. 4) Bulk limits (<= 25 payments per call). 5) All MCP actions logged in Events with source "App (GoCardless MCP)". 6) Separate Sandbox and Live connections and terms. 7) Access expires periodically; API tokens discouraged. | AB8: Standard | AC8: Two purposes in one server: integration help (no account access) and account management (after sign-in) | AD8: =COUNTIF(Actions!$A:$A,$A8) | AE8: 24 according to Composio (human-readable names; not officially confirmed). Support also mentions payment "retry", not in the catalogue. | AF8: Cannot be determined | AG8: Descriptions not published | AH8: Create customers and mandates directly (only payment links); manage account settings, users, webhooks; run Sandbox scenario simulators; see unmasked personal data and bank details; act outside the rights chosen at sign-in. | AI8: "Never share your API keys with your LLM"; use the sandbox during development; review generated code; give the AI only the necessary rights; test writing actions in Sandbox first; give the exact resource and amount and read the preview; check the AI provider's policy (free plans: "conversations may be used for AI training"); add "For any prompt that mentions GoCardless, use the GoCardless MCP" to prompts; agents without human review carry "extra risk" and the user is responsible for their actions. | AJ8: Masking of sensitive data, bank details never passed; log of all actions in Events. Terms: liability capped at £50 (9.5); processing personal data via MCP prohibited (4.1.5); the AI provider must use data only for the answer and delete it immediately (4.2.1, 4.2.4); the user is liable for breaches by the provider (4.3); no guarantee against "bias or hallucinations" (7.3); no guaranteed availability (2.4). | AK8: Two functions - "integration guidance and account management"; possibility to request a missing feature | AL8: Confirmation, masking, limits and log cannot be verified (closed code). Internal contradiction: the terms prohibit processing personal data via MCP, but the server returns customer data (masked). The requirement that the AI provider delete data immediately cannot be ensured by the user. | AM8: https://docs.gocardless.com/docs/developer-resources/mcp https://support.gocardless.com/hc/en-gb/articles/26830050176028-Use-AI-to-manage-your-account https://docs.gocardless.com/docs/developer-resources/mcp/terms https://docs.gocardless.com/docs/developer-resources/mcp/terms-sandbox https://mcp.gocardless.com/.well-known/oauth-protected-resource https://mcp.gocardless.com/.well-known/oauth-authorization-server https://composio.dev/toolkits/gocardless_mcp/framework/claude-cowork https://gocardless.com/pricing/ https://developer.gocardless.com/api-reference | AN8: CSV endpoint https://mcp.gocardless.com/mcp; docs give https://mcp.gocardless.com. The open-source gocardless-mcp by jmceleney on glama.ai is unofficial and not part of the analysis. Tool names in the catalogue are human-readable; real tools/list names may differ.
A9: airwallex | B9: Verified | C9: Manual analysis using Claude Opus 5.5 for verification and code analysis | D9: 2026-10-13 | E9: =((LEN(TRIM(I9))>0)*1+(LEN(TRIM(J9))>0)*1+(LEN(TRIM(K9))>0)*1+(LEN(TRIM(L9))>0)*1+(LEN(TRIM(M9))>0)*1+(LEN(TRIM(N9))>0)*1+(LEN(TRIM(O9))>0)*1+(LEN(TRIM(P9))>0)*1+(LEN(TRIM(Q9))>0)*1+(LEN(TRIM(R9))>0)*1+(LEN(TRIM(S9))>0)*1+(LEN(TRIM(T9))>0)*1+(LEN(TRIM(U9))>0)*1+(LEN(TRIM(V9))>0)*1+(LEN(TRIM(W9))>0)*1+(LEN(TRIM(X9))>0)*1+(LEN(TRIM(Y9))>0)*1+(LEN(TRIM(AA9))>0)*1+(LEN(TRIM(AB9))>0)*1+(LEN(TRIM(AC9))>0)*1+(LEN(TRIM(AE9))>0)*1+(LEN(TRIM(AF9))>0)*1+(LEN(TRIM(AG9))>0)*1+(LEN(TRIM(AH9))>0)*1+(LEN(TRIM(AI9))>0)*1+(LEN(TRIM(AJ9))>0)*1+(LEN(TRIM(AK9))>0)*1+(LEN(TRIM(AL9))>0)*1)/28 | F9: https://mcp.airwallex.com/mcp | G9: https://www.airwallex.com/docs/developer-tools/ai/agentos | H9: global | I9: Server closed; plugins and skills: https://github.com/airwallex/airwallex-marketplace | J9: https://www.airwallex.com/docs/developer-tools/ai/agentos (from CSV, incl. the .md version); https://www.airwallex.com/docs/developer-tools/ai/developer-connector.md | K9: No | L9: Not published | M9: 877551077786664d1cbeb32013443291c66e69e6 (skills repository; server not applicable) | N9: 2026-10-14 | O9: Not published | P9: Not published | Q9: No | R9: Server proprietary; skills/plugins Apache 2.0 | S9: Unknown | T9: No separate price for MCP given | U9: Paid | V9: EU plans: Explore €0 (with deposits/balance >= €10,000/month, otherwise €19/month), Grow €49/month, Accelerate custom; FX markup 0.5% (major currencies) / 1% (others); Core API included in Explore, fees may apply for additional access | W9: Monthly plan + FX markups for the financial platform | X9: OAuth to the production account with user-selected scopes ("grant only the OAuth scopes your use case needs"); no outgoing money operations (no write scopes for transfers/FX/payouts); Airwallex user rights and roles. Production only (sandbox is the separate Developer MCP). AgentOS skills are beta. Rate limits not documented. | Y9: Airwallex (scope set, money-out ban), user (scopes at sign-in) | Z9: =COUNTIFS(Capabilities!$A:$A,$A9,Capabilities!$C:$C,"Yes")+COUNTIFS(Capabilities!$A:$A,$A9,Capabilities!$C:$C,"Partially") | AA9: 1) Money-out ban at the level of rights: only read scopes for transfers and conversions ("AgentOS components do not initiate money-out actions"). 2) Writing tools annotated so that clients ask for confirmation (confirmation shown by the client). 3) Environment (production) declared in the server instructions. 4) Production only; sandbox is a separate server. 5) Rules in skills outside the server: never fabricate, stop and ask; name the environment and get explicit confirmation before irreversible operations; show the full payload before a write; "Do not provide financial advice"; CLI --dry-run -> confirm -> --confirm. 6) Feedback scope devx.feedback_write; skills tell the agent to offer feedback itself (with consent, no sensitive data). | AB9: Non-standard | AC9: Ecosystem of three separate servers by purpose and environment (AgentOS production / Developer sandbox / Docs) plus a common skills layer that works via MCP and CLI | AD9: =COUNTIF(Actions!$A:$A,$A9) | AE9: Exact number not published; reconstructed from OAuth scopes: 23 read and 12 write scopes (incl. feedback) + documentation search. The 12 tools in the Claude catalogue belong to the Developer MCP, not AgentOS. | AF9: Cannot be determined | AG9: Tool list not published | AH9: Transfers, payouts, currency exchange (dashboard only, "FX conversion: Airwallex Dashboard only"); get card number/CVV; delete a draft invoice, credit notes (CLI/dashboard only); work in the sandbox via AgentOS (needs the Developer MCP). | AI9: Turn off auto-approval modes ("Auto-Run", "Dangerously Skip Permissions"); confirm writes in the Airwallex web or mobile app; treat untrusted documents and web pages as prompt injection risk and review every tool call; do not paste API tokens; new chat for sensitive tasks; use a frontier model; install only trusted MCP servers alongside; do not add the agent to shared channels (Slack); grant only the necessary scopes. | AJ9: "AgentOS components do not initiate money-out actions" (confirmed by scopes). Writing tools annotated for confirmation. No privacy section in the MCP docs (link to Terms of Service). "Agent outputs are probabilistic". Logging of agent actions not described. | AK9: Tools so that agents "act on a production Airwallex account"; support for Claude Code, Claude Cowork, Cursor, Codex and others | AL9: "No money-out" confirmed by public OAuth metadata (no write scopes for transfers and FX). Annotations and instructions cannot be verified without signing in. | AM9: https://www.airwallex.com/docs/developer-tools/ai/agentos https://www.airwallex.com/docs/developer-tools/ai/agentos.md https://www.airwallex.com/docs/developer-tools/ai/developer-connector.md https://github.com/airwallex/airwallex-marketplace/tree/877551077786664d1cbeb32013443291c66e69e6 https://mcp.airwallex.com/.well-known/oauth-protected-resource/mcp https://mcp.airwallex.com/.well-known/oauth-authorization-server/mcp https://www.airwallex.com/de/pricing https://www.airwallex.com/docs/developer-tools/partner-connections/oauth-permissions https://claude.com/marketplace/connectors/airwallex | AN9: Tool list not published anywhere ("Discover tool names from your MCP client's tool list. Do not assume names"); actions reconstructed from the OAuth scopes. Meaning of pa_view not published (probably Payment Acceptance).
A10: braze | B10: Verified | C10: Manual analysis using Claude Opus 5.5 for verification and code analysis | D10: 2026-10-13 | E10: =((LEN(TRIM(I10))>0)*1+(LEN(TRIM(J10))>0)*1+(LEN(TRIM(K10))>0)*1+(LEN(TRIM(L10))>0)*1+(LEN(TRIM(M10))>0)*1+(LEN(TRIM(N10))>0)*1+(LEN(TRIM(O10))>0)*1+(LEN(TRIM(P10))>0)*1+(LEN(TRIM(Q10))>0)*1+(LEN(TRIM(R10))>0)*1+(LEN(TRIM(S10))>0)*1+(LEN(TRIM(T10))>0)*1+(LEN(TRIM(U10))>0)*1+(LEN(TRIM(V10))>0)*1+(LEN(TRIM(W10))>0)*1+(LEN(TRIM(X10))>0)*1+(LEN(TRIM(Y10))>0)*1+(LEN(TRIM(AA10))>0)*1+(LEN(TRIM(AB10))>0)*1+(LEN(TRIM(AC10))>0)*1+(LEN(TRIM(AE10))>0)*1+(LEN(TRIM(AF10))>0)*1+(LEN(TRIM(AG10))>0)*1+(LEN(TRIM(AH10))>0)*1+(LEN(TRIM(AI10))>0)*1+(LEN(TRIM(AJ10))>0)*1+(LEN(TRIM(AK10))>0)*1+(LEN(TRIM(AL10))>0)*1)/28 | F10: https://mcp.braze.com/mcp | G10: https://www.braze.com/docs/user_guide/brazeai/mcp_server | H10: global | I10: Remote server closed; deprecated local server only as PyPI package https://pypi.org/project/braze-mcp-server/ (no public repository found) | J10: https://www.braze.com/docs/user_guide/brazeai/mcp_server (from CSV); https://www.braze.com/docs/developer_guide/mcp_server/; setup, usage and available_api_functions pages | K10: No | L10: Not published | M10: Not applicable (closed code) | N10: Documentation snapshot 2026-10-13 | O10: Remote: not published; deprecated local: Python >= 3.12 | P10: Not published | Q10: No | R10: Remote proprietary; deprecated local package MIT | S10: Unknown | T10: No price given; available to Braze customers | U10: Paid | V10: Proprietary enterprise platform; no public prices (by contract) | W10: Enterprise contract | X10: Permission "Use MCP Server" off by default, granted per workspace; the company administrator must enable MCP OAuth and approve the client's redirect URI; only allowlisted AI clients (Claude, ChatGPT, Cursor, OpenAI Codex, Claude Code, VS Code); agent rights = dashboard rights, checked per request; does not work with IP Allowlisting; asterisked tools need the campaigns API beta program. Rate limits not documented. | Y10: Company administrator in Braze (OAuth, permissions, mass token revocation); Braze (client allowlist, beta program) | Z10: =COUNTIFS(Capabilities!$A:$A,$A10,Capabilities!$C:$C,"Yes")+COUNTIFS(Capabilities!$A:$A,$A10,Capabilities!$C:$C,"Partially") | AA10: 1) PII excluded by design (no user-level tools; only aggregates and configuration). 2) Dashboard rights inherited and checked per request; deactivated users lose access immediately. 3) Multi-level access: "Use MCP Server" permission (off by default) + OAuth enabled by admin + redirect URI approval + client allowlist. 4) Batch limits (catalogues <= 50 items) and pagination. 5) Campaign edits recorded under the user's name in the change history. 6) Nested agent: send_operator_prompt hands tasks to BrazeAI Operator in the background. 7) Beta gating (15 campaign tools, 3 segment tools). 8) No server-side confirmation: "Braze receives and executes the tool call as the AI model sends it". | AB10: Standard | AC10: Standard, but with a nested vendor agent (BrazeAI Operator); two regional endpoints (US mcp.braze.com, EU mcp.braze.eu), each works with any cluster | AD10: =COUNTIF(Actions!$A:$A,$A10) | AE10: 71 according to the documentation: 37 reading, 34 changing; 18 require the beta program | AF10: Cannot be determined | AG10: Exact descriptions and schemas not published; with 71 tools probably considerable | AH10: User data (PII): profiles, export, deletion; Canvas is read-only; send messages directly (Messaging API); drag-and-drop templates; delete templates and content blocks; administration (users, rights, API keys, company settings); without beta: create/edit campaigns and segments. | AI10: Do not use auto-mode in the AI client; "review any AI-proposed action before implementing it"; "Compare high-impact recommendations against source data"; name the workspace explicitly in every request (production vs staging), otherwise the agent may "choose an unexpected workspace"; specify dates and metrics; ask the agent which tools it used. | AJ10: "non-PII Braze data" / "Tools that expose user-level PII are not available"; "An agent can never exceed your own access"; campaign edits visible in the change history; "Braze does not see your original natural-language prompt"; disclaimer: Braze "not liable for instructions generated by, or responses conveyed through, third-party MCP clients"; privacy policy: Braze is processor for customer data, "We maintain human oversight and do not make decisions based solely on automated processing" (Braze's own AI); no overall MCP activity log described. | AK10: "a secure remote connection that lets AI tools like Claude and Cursor access non-PII Braze data"; one connector for all accessible workspaces | AL10: "non-PII" consistent with the tool list (no user export, only aggregates and configuration), but catalogues, media and content blocks can contain any data the customer uploaded - not discussed. | AM10: https://www.braze.com/docs/user_guide/brazeai/mcp_server https://www.braze.com/docs/developer_guide/mcp_server/ https://www.braze.com/docs/user_guide/brazeai/mcp_server/setup/ https://www.braze.com/docs/user_guide/brazeai/mcp_server/usage/ https://braze.com/docs/developer_guide/mcp_server/available_api_functions/ https://mcp.braze.com/.well-known/oauth-protected-resource https://pypi.org/project/braze-mcp-server/ https://www.braze.com/company/legal/privacy | AN10: Tool list from the official documentation (names and short descriptions); exact tools/list not verifiable without signing in. Local server (PyPI 1.2.0, 14.05.2026) deprecated and smaller than the remote one.
A11: clickup | B11: Verified | C11: Manual analysis using Claude Opus 5.5 for verification and code analysis | D11: 2026-10-14 | E11: =((LEN(TRIM(I11))>0)*1+(LEN(TRIM(J11))>0)*1+(LEN(TRIM(K11))>0)*1+(LEN(TRIM(L11))>0)*1+(LEN(TRIM(M11))>0)*1+(LEN(TRIM(N11))>0)*1+(LEN(TRIM(O11))>0)*1+(LEN(TRIM(P11))>0)*1+(LEN(TRIM(Q11))>0)*1+(LEN(TRIM(R11))>0)*1+(LEN(TRIM(S11))>0)*1+(LEN(TRIM(T11))>0)*1+(LEN(TRIM(U11))>0)*1+(LEN(TRIM(V11))>0)*1+(LEN(TRIM(W11))>0)*1+(LEN(TRIM(X11))>0)*1+(LEN(TRIM(Y11))>0)*1+(LEN(TRIM(AA11))>0)*1+(LEN(TRIM(AB11))>0)*1+(LEN(TRIM(AC11))>0)*1+(LEN(TRIM(AE11))>0)*1+(LEN(TRIM(AF11))>0)*1+(LEN(TRIM(AG11))>0)*1+(LEN(TRIM(AH11))>0)*1+(LEN(TRIM(AI11))>0)*1+(LEN(TRIM(AJ11))>0)*1+(LEN(TRIM(AK11))>0)*1+(LEN(TRIM(AL11))>0)*1)/28 | F11: https://mcp.clickup.com/mcp | G11: https://developer.clickup.com/docs/connect-an-ai-assistant-to-clickups-mcp-server | H11: global | I11: Not published | J11: https://developer.clickup.com/docs/connect-an-ai-assistant-to-clickups-mcp-server (from CSV); https://developer.clickup.com/docs/mcp-tools | K11: Unknown | L11: Not published | M11: Not applicable (closed code) | N11: Documentation snapshot 2026-10-14 | O11: Not published | P11: Not published | Q11: No | R11: Proprietary | S11: Free | T11: Available on all plans, no separate fee; MCP does not consume AI credits | U11: Freemium | V11: Free Forever $0; Unlimited $7 (annual) / $10 (monthly) per user; Business $12/$19; Enterprise on request. The same page also shows Core $9, Business $17, Max $100 (contradictory). Everything AI add-on $28 per user/month. | W11: Per-user plans; MCP call limits depend on the plan and the Everything AI add-on | X11: Calls per rolling 24 h without Everything AI: Free 100, Core/Unlimited 300, Business 1,000, Business Plus 2,500, Enterprise 5,000, Enterprise Plus 25,000 - per workspace and per AI client separately; initialize and tools/list not counted; with the add-on - public API limits; RATE_LIMIT_EXCEEDED with retryAfter, cannot be reset. OAuth only (no personal API keys); rights = the user's ClickUp rights; AI fair use policy. | Y11: ClickUp (plans, limits, fair use), workspace administrator (user rights) | Z11: =COUNTIFS(Capabilities!$A:$A,$A11,Capabilities!$C:$C,"Yes")+COUNTIFS(Capabilities!$A:$A,$A11,Capabilities!$C:$C,"Partially") | AA11: 1) Daily call limits per AI client and workspace (plan-dependent). 2) Deletion restricted "as a safety measure for now" - but the tool list contains "Delete task" (the assistant "may confirm") - contradiction. 3) The user's ClickUp rights are inherited. 4) Server-side confirmation and agent action log not described. 5) Connected Search not available via MCP. | AB11: Standard | AC11: Flat set of tools | AD11: =COUNTIF(Actions!$A:$A,$A11) | AE11: 48 according to the Supported Tools page (human-readable names) | AF11: Cannot be determined | AG11: Descriptions not published | AH11: Delete lists, folders, spaces, documents, comments (only tasks); manage members and rights; automations; goals, dashboards, whiteboards; Connected Search across external apps. | AI11: No explicit recommendations on human confirmation (except "may confirm" before deleting a task). | AJ11: Only links to security, privacy and AI fair use policies; no specific promises about data passed to the AI. | AK11: "available on all plans"; limits "may change", "future restrictions" possible | AL11: The "no deletion" statement contradicts the tool "Delete task". | AM11: https://developer.clickup.com/docs/connect-an-ai-assistant-to-clickups-mcp-server https://developer.clickup.com/docs/mcp-tools https://mcp.clickup.com/.well-known/oauth-protected-resource https://mcp.clickup.com/.well-known/oauth-authorization-server https://clickup.com/pricing https://developer.clickup.com/llms.txt | AN11: Endpoint https://mcp.clickup.com/mcp; data from https://api.clickup.com (resource_server_origin). Tool names are human-readable (docs); exact tools/list not available without sign-in.
A12: motion | B12: Verified | C12: Manual analysis using Claude Opus 5.5 for verification and code analysis | D12: 2026-10-14; re-analysed 2026-10-23 (new commit in the repository) | E12: =((LEN(TRIM(I12))>0)*1+(LEN(TRIM(J12))>0)*1+(LEN(TRIM(K12))>0)*1+(LEN(TRIM(L12))>0)*1+(LEN(TRIM(M12))>0)*1+(LEN(TRIM(N12))>0)*1+(LEN(TRIM(O12))>0)*1+(LEN(TRIM(P12))>0)*1+(LEN(TRIM(Q12))>0)*1+(LEN(TRIM(R12))>0)*1+(LEN(TRIM(S12))>0)*1+(LEN(TRIM(T12))>0)*1+(LEN(TRIM(U12))>0)*1+(LEN(TRIM(V12))>0)*1+(LEN(TRIM(W12))>0)*1+(LEN(TRIM(X12))>0)*1+(LEN(TRIM(Y12))>0)*1+(LEN(TRIM(AA12))>0)*1+(LEN(TRIM(AB12))>0)*1+(LEN(TRIM(AC12))>0)*1+(LEN(TRIM(AE12))>0)*1+(LEN(TRIM(AF12))>0)*1+(LEN(TRIM(AG12))>0)*1+(LEN(TRIM(AH12))>0)*1+(LEN(TRIM(AI12))>0)*1+(LEN(TRIM(AJ12))>0)*1+(LEN(TRIM(AK12))>0)*1+(LEN(TRIM(AL12))>0)*1)/28 | F12: https://mcp.motion.dev/mcp | G12: https://motion.dev/docs/ai-kit | H12: global | I12: Server closed; skills/plugin/installer: https://github.com/motiondivision/ai-kit | J12: https://motion.dev/docs/ai-kit (from CSV); https://mcp.motion.dev/mcp (server page); https://motion.dev/plus | K12: No | L12: 2025-06-18 (stated by the server) | M12: 0ebeb5313a069986376430f665415252e223d1d4 (ai-kit repository; server not applicable) | N12: 2026-10-23 | O12: Not published | P12: Not published | Q12: No | R12: Server proprietary; ai-kit MIT | S12: Freemium | T12: Free server: "Documentation search is free. No token, account or configuration is required." Motion+ (separate endpoint /plus): one-time purchase per developer ("Pay once", "Yours forever"; amount did not load); annual Pro add-on (AI agent Ultramotion) | U12: Open source | V12: Motion library free (MIT) | W12: Free documentation search; one-time Motion+ license; annual Pro add-on | X12: Paid features need Motion+ sign-in; the performance audit only profiles a "running local site" | Y12: Motion (license tiers) | Z12: =COUNTIFS(Capabilities!$A:$A,$A12,Capabilities!$C:$C,"Yes")+COUNTIFS(Capabilities!$A:$A,$A12,Capabilities!$C:$C,"Partially") | AA12: 1) Monetisation via tool responses: "the rest is tiered, and the tools say so when you reach them" - the free tool tells the agent about paid features. 2) Two servers by access level (free / plus). 3) The performance evaluation methodology (MotionScore) is defined and changed on the server side and delivered at call time. 4) Behaviour rules in skills. | AB12: Non-standard | AC12: Two servers (free / plus) plus skills and a reviewer agent (plugins/motion/agents/motion-reviewer.md) in a separate repository | AD12: =COUNTIF(Actions!$A:$A,$A12) | AE12: Free server: 1 (search-motion-docs). Plus: not published (at least 4 groups: audit, example source code, springs, transition editor) | AF12: Cannot be determined (minimal with one tool) | AG12: Description not published | AH12: Without Motion+: generate springs, run the audit, get example and Motion UI source code; the agent cannot buy a license. | AI12: None | AJ12: Data processing and telemetry not described; the Motion+ audit analyses the user's project source code - what is sent to the server is not described. | AK12: "Hand-written advice by the creator of Motion"; "Nothing gets pasted into chat" (about sign-in) | AL12: Cannot be compared (closed code, no governance statements) | AM12: https://motion.dev/docs/ai-kit https://mcp.motion.dev/mcp https://github.com/motiondivision/ai-kit/tree/0ebeb5313a069986376430f665415252e223d1d4 https://motion.dev/plus | AN12: Not the Motion calendar (usemotion.com). Endpoints: free https://mcp.motion.dev (CSV: /mcp), paid https://mcp.motion.dev/plus. Direct requests from our environment were blocked by the network policy (the CSV records HTTP 200 without sign-in).
A13: quo | B13: Verified | C13: Manual analysis using Claude Opus 5.5 for verification and code analysis | D13: 2026-10-14 | E13: =((LEN(TRIM(I13))>0)*1+(LEN(TRIM(J13))>0)*1+(LEN(TRIM(K13))>0)*1+(LEN(TRIM(L13))>0)*1+(LEN(TRIM(M13))>0)*1+(LEN(TRIM(N13))>0)*1+(LEN(TRIM(O13))>0)*1+(LEN(TRIM(P13))>0)*1+(LEN(TRIM(Q13))>0)*1+(LEN(TRIM(R13))>0)*1+(LEN(TRIM(S13))>0)*1+(LEN(TRIM(T13))>0)*1+(LEN(TRIM(U13))>0)*1+(LEN(TRIM(V13))>0)*1+(LEN(TRIM(W13))>0)*1+(LEN(TRIM(X13))>0)*1+(LEN(TRIM(Y13))>0)*1+(LEN(TRIM(AA13))>0)*1+(LEN(TRIM(AB13))>0)*1+(LEN(TRIM(AC13))>0)*1+(LEN(TRIM(AE13))>0)*1+(LEN(TRIM(AF13))>0)*1+(LEN(TRIM(AG13))>0)*1+(LEN(TRIM(AH13))>0)*1+(LEN(TRIM(AI13))>0)*1+(LEN(TRIM(AJ13))>0)*1+(LEN(TRIM(AK13))>0)*1+(LEN(TRIM(AL13))>0)*1)/28 | F13: https://mcp.quo.com/mcp | G13: https://support.quo.com/core-concepts/integrations/mcp | H13: global | I13: Not published | J13: https://support.quo.com/core-concepts/integrations/mcp (from CSV); https://claude.com/connectors/quo | K13: Unknown | L13: Not published | M13: Not applicable (closed code) | N13: Documentation snapshot 2026-10-14 | O13: Not published | P13: Not published | Q13: No | R13: Proprietary | S13: Free | T13: "ChatGPT / Claude MCP" included in all plans at no extra charge; sending SMS via the AI assistant needs pre-paid credits | U13: Paid | V13: Starter $19/$15, Business $33/$23, Scale $47/$35 per user/month (monthly/annual); automation credits (1,000 free = 10 Sona AI agent calls; packages $25-$199/month); automated SMS via API $0.01 per segment | W13: Per-user plans + credits for automation and SMS | X13: Clients: Claude all users, ChatGPT Plus and Pro, Grok users. SMS only with pre-paid credits. Transcripts only on numbers where enabled. | Y13: Quo (plans, credits) | Z13: =COUNTIFS(Capabilities!$A:$A,$A13,Capabilities!$C:$C,"Yes")+COUNTIFS(Capabilities!$A:$A,$A13,Capabilities!$C:$C,"Partially") | AA13: 1) Pre-paid credits limit SMS sending by the agent. 2) OAuth scopes broader than the documentation (write:calls, read:agents, write:agents) - needs checking. 3) Confirmation before sending, bulk limits and logging not described. | AB13: Standard | AC13: According to the available information | AD13: =COUNTIF(Actions!$A:$A,$A13) | AE13: Not published; 6 capability groups in the docs (summaries, sending SMS, messages/inboxes, calls/transcripts, contacts, missed calls); scopes also point to call writing and AI agents | AF13: Cannot be determined | AG13: Tool list not published | AH13: Make calls (not stated in docs, although write:calls exists); manage numbers, users, billing; send SMS without credits. | AI13: None; nothing about confirming messages before sending. | AJ13: Not described in the MCP docs (link to the privacy policy). The agent has access to customer conversations and call transcripts (third-party personal data). | AK13: "Surface call insights and missed opportunities" | AL13: OAuth scopes reveal more capabilities (calls, AI agents) than the documentation describes. | AM13: https://support.quo.com/core-concepts/integrations/mcp https://claude.com/connectors/quo https://mcp.quo.com/.well-known/oauth-protected-resource https://mcp.quo.com/.well-known/oauth-authorization-server https://www.quo.com/pricing https://quo.com/privacy https://quo.com/blog/next-chapter/ | AN13: Quo = formerly OpenPhone. Official connector for Claude, ChatGPT, Grok. Actions reconstructed from documentation capability groups and OAuth scopes.
A14: tripadvisor | B14: Verified | C14: Manual analysis using Claude Opus 5.5 for verification and code analysis | D14: 2026-10-14 | E14: =((LEN(TRIM(I14))>0)*1+(LEN(TRIM(J14))>0)*1+(LEN(TRIM(K14))>0)*1+(LEN(TRIM(L14))>0)*1+(LEN(TRIM(M14))>0)*1+(LEN(TRIM(N14))>0)*1+(LEN(TRIM(O14))>0)*1+(LEN(TRIM(P14))>0)*1+(LEN(TRIM(Q14))>0)*1+(LEN(TRIM(R14))>0)*1+(LEN(TRIM(S14))>0)*1+(LEN(TRIM(T14))>0)*1+(LEN(TRIM(U14))>0)*1+(LEN(TRIM(V14))>0)*1+(LEN(TRIM(W14))>0)*1+(LEN(TRIM(X14))>0)*1+(LEN(TRIM(Y14))>0)*1+(LEN(TRIM(AA14))>0)*1+(LEN(TRIM(AB14))>0)*1+(LEN(TRIM(AC14))>0)*1+(LEN(TRIM(AE14))>0)*1+(LEN(TRIM(AF14))>0)*1+(LEN(TRIM(AG14))>0)*1+(LEN(TRIM(AH14))>0)*1+(LEN(TRIM(AI14))>0)*1+(LEN(TRIM(AJ14))>0)*1+(LEN(TRIM(AK14))>0)*1+(LEN(TRIM(AL14))>0)*1)/28 | F14: https://mcp.tripadvisor.ai/mcp | H14: global | I14: Not published | J14: No official documentation; https://claude.com/connectors/tripadvisor (connector card); https://mcpservers.org/remote-mcp-servers/tripadvisor (third-party catalogue) | K14: Unknown | L14: Not published | M14: Not applicable (closed code) | N14: Documentation snapshot 2026-10-14 | O14: Not published | P14: Not published | Q14: No | R14: Proprietary | S14: Unknown | T14: No price given; connector available in Claude (web, desktop, mobile, Code, API) | U14: Unknown | V14: Tripadvisor is free for travellers | W14: Not documented | X14: Endpoint returns 403 without sign-in (CSV); authorization method not documented | Y14: Unknown | Z14: =COUNTIFS(Capabilities!$A:$A,$A14,Capabilities!$C:$C,"Yes")+COUNTIFS(Capabilities!$A:$A,$A14,Capabilities!$C:$C,"Partially") | AA14: Clarification of ambiguous places before searching; read only, no booking; everything else not documented. | AB14: Standard | AC14: According to the available information; hosted on a separate platform ("ai-mcp-extensibility" on tamg.cloud) behind mcp.tripadvisor.ai | AD14: =COUNTIF(Actions!$A:$A,$A14) | AE14: Not published; 4 functions according to the description (hotel search, hotel details, prices and availability, places nearby) | AF14: Cannot be determined | AG14: Tool list not published | AH14: Book; work with restaurants and attractions (hotels only); write reviews; manage Trips. | AI14: None (practically no documentation) | AJ14: Practically none; the privacy policy in the connector card is the 2019 version. | AK14: "Find your perfect hotel based on Tripadvisor reviews", "ground accommodation planning in real-time data and other travelers' opinions" | AL14: Cannot be compared (no documentation, closed code) | AM14: https://claude.com/connectors/tripadvisor https://mcpservers.org/remote-mcp-servers/tripadvisor | AN14: CSV has no documentation link. The catalogue gives a different address: https://production.ai-mcp-extensibility-prd.tamg.cloud/ogMvjY4De1G7CiHanMOAgddl/mcp (tamg = TripAdvisor Media Group). Unofficial tripadvisor-mcp servers on GitHub (pab1it0, hhw67865) not included. Support: TripadvisorDataSupport@tripadvisor.com.
A15: brex | B15: Verified | C15: Manual analysis using Claude Opus 5.5 for verification and code analysis | D15: 2026-10-15 | E15: =((LEN(TRIM(I15))>0)*1+(LEN(TRIM(J15))>0)*1+(LEN(TRIM(K15))>0)*1+(LEN(TRIM(L15))>0)*1+(LEN(TRIM(M15))>0)*1+(LEN(TRIM(N15))>0)*1+(LEN(TRIM(O15))>0)*1+(LEN(TRIM(P15))>0)*1+(LEN(TRIM(Q15))>0)*1+(LEN(TRIM(R15))>0)*1+(LEN(TRIM(S15))>0)*1+(LEN(TRIM(T15))>0)*1+(LEN(TRIM(U15))>0)*1+(LEN(TRIM(V15))>0)*1+(LEN(TRIM(W15))>0)*1+(LEN(TRIM(X15))>0)*1+(LEN(TRIM(Y15))>0)*1+(LEN(TRIM(AA15))>0)*1+(LEN(TRIM(AB15))>0)*1+(LEN(TRIM(AC15))>0)*1+(LEN(TRIM(AE15))>0)*1+(LEN(TRIM(AF15))>0)*1+(LEN(TRIM(AG15))>0)*1+(LEN(TRIM(AH15))>0)*1+(LEN(TRIM(AI15))>0)*1+(LEN(TRIM(AJ15))>0)*1+(LEN(TRIM(AK15))>0)*1+(LEN(TRIM(AL15))>0)*1)/28 | F15: https://api.brex.com/mcp | G15: https://developer.brex.com/docs/mcp | H15: global | I15: Not published | J15: https://developer.brex.com/docs/mcp (from CSV) | K15: Unknown | L15: Not published | M15: Not applicable (closed code) | N15: Documentation snapshot 2026-10-15 | O15: Not published | P15: Not published | Q15: No | R15: Proprietary | S15: Free | T15: No separate price; requires the Developer API agreement accepted by an admin and the beta "Brex in AI assistants" enabled | U15: Freemium | V15: Essentials $0/user/month; Premium $12; Enterprise and Smart Card on request | W15: Per-user plans | X15: Account or card admin accepts the Developer API agreement and enables the beta; access = the user's Brex capabilities; some tools need separate rights (viewing expenses, bills, accounting ...); brex-analytics admins only. Beta: tools "may change". Rate limits not documented. | Y15: Brex administrator (agreement, beta, roles), Brex | Z15: =COUNTIFS(Capabilities!$A:$A,$A15,Capabilities!$C:$C,"Yes")+COUNTIFS(Capabilities!$A:$A,$A15,Capabilities!$C:$C,"Partially") | AA15: 1) Every tool requires its own capability; without it the tool does not work. 2) Card PAN, CVV and expiry hidden at server level. 3) Money operations excluded ("approvals and card management are not yet available via MCP") - but write scopes cards and expenses.bill exist. 4) Tool deprecation (query_expense_analytics -> brex-analytics). 5) No server-side confirmation declared; recommended in the client. | AB15: Standard | AC15: Standard; brex-analytics is an analytical "super-tool" for admins (free-form questions about expenses, banking, accounting) | AD15: =COUNTIF(Actions!$A:$A,$A15) | AE15: Docs: 44 active + 1 deprecated (query_expense_analytics). The tool table in the manual analysis lists 43 active names + the deprecated one. | AF15: Cannot be determined | AG15: Descriptions not published | AH15: Approve expenses; issue or block cards, change limits; pay bills and make transfers; see card details. | AI15: Configure confirmation before actions in the assistant; prefer OAuth; use restricted tokens; keep tokens in environment variables; review the API logs in the dashboard. | AJ15: PAN/CVV/expiry not disclosed; rights = the user's capabilities. Nothing about data storage or use by the AI provider. | AK15: Not stated beyond the tool list (beta) | AL15: "Card management not available" does not match the write scope cards - either requested in advance or the documentation is behind. | AM15: https://developer.brex.com/docs/mcp https://api.brex.com/.well-known/oauth-protected-resource/mcp https://www.brex.com/pricing | AN15: Endpoint https://api.brex.com/mcp (beta). OAuth scopes are broader than the documented tools (cards, expenses.bill).
A16: calendly | B16: Verified | C16: Manual analysis using Claude Opus 5.5 for verification and code analysis | D16: 2026-10-15 | E16: =((LEN(TRIM(I16))>0)*1+(LEN(TRIM(J16))>0)*1+(LEN(TRIM(K16))>0)*1+(LEN(TRIM(L16))>0)*1+(LEN(TRIM(M16))>0)*1+(LEN(TRIM(N16))>0)*1+(LEN(TRIM(O16))>0)*1+(LEN(TRIM(P16))>0)*1+(LEN(TRIM(Q16))>0)*1+(LEN(TRIM(R16))>0)*1+(LEN(TRIM(S16))>0)*1+(LEN(TRIM(T16))>0)*1+(LEN(TRIM(U16))>0)*1+(LEN(TRIM(V16))>0)*1+(LEN(TRIM(W16))>0)*1+(LEN(TRIM(X16))>0)*1+(LEN(TRIM(Y16))>0)*1+(LEN(TRIM(AA16))>0)*1+(LEN(TRIM(AB16))>0)*1+(LEN(TRIM(AC16))>0)*1+(LEN(TRIM(AE16))>0)*1+(LEN(TRIM(AF16))>0)*1+(LEN(TRIM(AG16))>0)*1+(LEN(TRIM(AH16))>0)*1+(LEN(TRIM(AI16))>0)*1+(LEN(TRIM(AJ16))>0)*1+(LEN(TRIM(AK16))>0)*1+(LEN(TRIM(AL16))>0)*1)/28 | F16: https://mcp.calendly.com/ | G16: https://developer.calendly.com/calendly-mcp-server | H16: global | I16: Not published ("Self-hosting or local deployment is not supported") | J16: https://developer.calendly.com/calendly-mcp-server (from CSV); https://developer.calendly.com/docs/mcp/supported-tools | K16: Unknown | L16: Not published | M16: Not applicable (closed code) | N16: Documentation snapshot 2026-10-15 | O16: Not published | P16: Not published | Q16: No | R16: Proprietary | S16: Unknown | T16: No price given | U16: Freemium | V16: Free; Standard $10; Teams $16 per seat/month; Enterprise from $15,000/year (50+ seats) | W16: Per-seat plans; some tools depend on the plan | X16: meetings-create_invitee (booking) requires a paid plan; routing forms Teams and above. OAuth via DCR only (no personal tokens, no pre-registered apps); DCR "heavily validated and rate-limited"; other limits not given. | Y16: Calendly (plans, client policy) | Z16: =COUNTIFS(Capabilities!$A:$A,$A16,Capabilities!$C:$C,"Yes")+COUNTIFS(Capabilities!$A:$A,$A16,Capabilities!$C:$C,"Partially") | AA16: 1) Separate read and write scopes, assigned by the server. 2) Strict client policy: DCR only, no secrets, exact redirect URIs. 3) Server-side skills loaded on demand control the agent's behaviour. 4) Plan restrictions at tool level. 5) No confirmation of individual actions; only consent at sign-in. | AB16: Standard | AC16: Flat set of tools mirroring REST API v2, plus 2 skill tools | AD16: =COUNTIF(Actions!$A:$A,$A16) | AE16: 36: 34 correspond to REST API v2 (23 GET, 11 POST/PATCH/PUT/DELETE), 2 skill tools | AF16: Cannot be determined | AG16: Descriptions not published | AH16: Delete event types; remove organisation members (only invitations); webhooks, calendar integrations, payments, workflows; Data Deletion API (Enterprise). | AI16: No recommendations on confirming actions. | AJ16: Nothing about data, only a link to the privacy notice. The agent sees invitee data (third parties) and routing form answers. | AK16: Works with any client that supports DCR | AL16: Cannot be compared (closed code, no governance statements) | AM16: https://developer.calendly.com/calendly-mcp-server https://developer.calendly.com/docs/mcp/supported-tools https://mcp.calendly.com/.well-known/oauth-protected-resource https://calendly.com/.well-known/oauth-authorization-server https://calendly.com/pricing | AN16: Endpoint https://mcp.calendly.com (CSV with trailing slash). Tool annotations present (title, readOnlyHint, destructiveHint, idempotentHint). Descriptions in the docs are paraphrased.
A17: context7 | B17: Verified | C17: Manual analysis using Claude Opus 5.5 for verification and code analysis | D17: 2026-10-15; re-analysed 2026-10-23 (new commit in the repository) | E17: =((LEN(TRIM(I17))>0)*1+(LEN(TRIM(J17))>0)*1+(LEN(TRIM(K17))>0)*1+(LEN(TRIM(L17))>0)*1+(LEN(TRIM(M17))>0)*1+(LEN(TRIM(N17))>0)*1+(LEN(TRIM(O17))>0)*1+(LEN(TRIM(P17))>0)*1+(LEN(TRIM(Q17))>0)*1+(LEN(TRIM(R17))>0)*1+(LEN(TRIM(S17))>0)*1+(LEN(TRIM(T17))>0)*1+(LEN(TRIM(U17))>0)*1+(LEN(TRIM(V17))>0)*1+(LEN(TRIM(W17))>0)*1+(LEN(TRIM(X17))>0)*1+(LEN(TRIM(Y17))>0)*1+(LEN(TRIM(AA17))>0)*1+(LEN(TRIM(AB17))>0)*1+(LEN(TRIM(AC17))>0)*1+(LEN(TRIM(AE17))>0)*1+(LEN(TRIM(AF17))>0)*1+(LEN(TRIM(AG17))>0)*1+(LEN(TRIM(AH17))>0)*1+(LEN(TRIM(AI17))>0)*1+(LEN(TRIM(AJ17))>0)*1+(LEN(TRIM(AK17))>0)*1+(LEN(TRIM(AL17))>0)*1)/28 | F17: https://mcp.context7.com/mcp | G17: https://context7.com/docs/mcp | H17: global | I17: https://github.com/upstash/context7 (packages/mcp) | J17: https://github.com/upstash/context7/blob/b5e81de845092694ba1bfc5af15400f319c89b6d/README.md; https://context7.com/plans | K17: Yes | L17: 2026-07-28 (stateless, _meta envelope) + 2025 versions via legacy fallback | M17: b5e81de845092694ba1bfc5af15400f319c89b6d | N17: 2026-10-23 | O17: TypeScript (Node.js) | P17: Official SDK v2: @modelcontextprotocol/server 2.3.1, @modelcontextprotocol/node 2.1.1 | Q17: Partially | R17: MIT (c) 2021 Upstash | S17: Freemium | T17: Anonymous access possible; free key gives higher limits. Free $0: 1,000 API calls/month, then blocked + 20 bonus calls/day, public repositories only. Pro $10/seat/month: 2,000 calls per seat, then $5 per 1,000; private repositories (parsing $5 per 1M tokens). Enterprise on request (SOC-2, SSO, self-hosted). | U17: Freemium | V17: Context7 service (documentation index) is closed; prices as above | W17: Monthly API call quotas per plan; overage per 1,000 calls; private repository parsing per token | X17: Teamspace library filters ("quality thresholds or blocked libraries") set by the team administrator; rate limits by plan; OAuth required on /mcp/oauth | Y17: Context7/Upstash (plans), team administrator (teamspace filters) | Z17: =COUNTIFS(Capabilities!$A:$A,$A17,Capabilities!$C:$C,"Yes")+COUNTIFS(Capabilities!$A:$A,$A17,Capabilities!$C:$C,"Partially") | AA17: 1) Rewrites hallucinated argument names (userQuery/question -> query; libraryName/libraryID -> libraryId). 2) "Do not call this tool more than 3 times per question" (text only). 3) "Do not include any sensitive or confidential information..." in query descriptions (text only). 4) Source Reputation and Benchmark Score passed to the AI. 5) Teamspace quality filters/blocked libraries applied on the API side with a note to the AI. 6) Telemetry: server version, transport, IDE/client version, plugin, session ID, encrypted client IP assertion sent with every request; OpenTelemetry/Prometheus. 7) Sign-up prompts for anonymous users via elicitation (max once per session). 8) Instructions: use Context7 even if the AI knows the answer and prefer it over web search. | AB17: Standard | AC17: Stateless (new server instance per request); a separate admin-mcp server in the same repository (not in the CSV) | AD17: =COUNTIF(Actions!$A:$A,$A17) | AE17: 2 tools | AF17: ~1,900 | AG17: Instructions + 2 tools, characters / 4 from the code | AH17: Add or update libraries in the index; manage private repositories, teamspace policies, keys and the plan (context7.com dashboard). | AI17: Do not pass secrets or personal data in queries (parameter descriptions); do not call more than 3 times per question. | AJ17: "The query is sent to the Context7 API for processing"; no separate processing policy in the MCP documentation. | AK17: "up-to-date documentation and code examples"; a key gives "higher rate limits" | AL17: The "3 calls" and "no secrets" restrictions are text only, not enforced by the code. | AM17: https://github.com/upstash/context7/tree/b5e81de845092694ba1bfc5af15400f319c89b6d https://github.com/upstash/context7/blob/b5e81de845092694ba1bfc5af15400f319c89b6d/packages/mcp/src/index.ts https://context7.com/plans https://mcp.context7.com/.well-known/oauth-protected-resource | AN17: The open package @upstash/context7-mcp 4.4.4 is the same server as mcp.context7.com (RESOURCE_URL in lib/constants.ts), but search and documentation come from the closed Context7 API (/v2/libs/search, /v2/context). Endpoint https://mcp.context7.com/mcp (+ /mcp/oauth with mandatory OAuth).
A18: heroku | B18: Verified | C18: Manual analysis using Claude Opus 5.5 for verification and code analysis | D18: 2026-10-15 | E18: =((LEN(TRIM(I18))>0)*1+(LEN(TRIM(J18))>0)*1+(LEN(TRIM(K18))>0)*1+(LEN(TRIM(L18))>0)*1+(LEN(TRIM(M18))>0)*1+(LEN(TRIM(N18))>0)*1+(LEN(TRIM(O18))>0)*1+(LEN(TRIM(P18))>0)*1+(LEN(TRIM(Q18))>0)*1+(LEN(TRIM(R18))>0)*1+(LEN(TRIM(S18))>0)*1+(LEN(TRIM(T18))>0)*1+(LEN(TRIM(U18))>0)*1+(LEN(TRIM(V18))>0)*1+(LEN(TRIM(W18))>0)*1+(LEN(TRIM(X18))>0)*1+(LEN(TRIM(Y18))>0)*1+(LEN(TRIM(AA18))>0)*1+(LEN(TRIM(AB18))>0)*1+(LEN(TRIM(AC18))>0)*1+(LEN(TRIM(AE18))>0)*1+(LEN(TRIM(AF18))>0)*1+(LEN(TRIM(AG18))>0)*1+(LEN(TRIM(AH18))>0)*1+(LEN(TRIM(AI18))>0)*1+(LEN(TRIM(AJ18))>0)*1+(LEN(TRIM(AK18))>0)*1+(LEN(TRIM(AL18))>0)*1)/28 | F18: https://mcp.heroku.com/mcp | G18: https://devcenter.heroku.com/articles/heroku-mcp-server | H18: global | I18: https://github.com/heroku/heroku-mcp-server (local stdio server; the remote server at the CSV endpoint is closed) | J18: https://devcenter.heroku.com/articles/heroku-mcp-server (from CSV); https://devcenter.heroku.com/articles/heroku-remote-mcp-server; https://www.heroku.com/blog/heroku-remote-mcp-server/ | K18: No | L18: Local: @modelcontextprotocol/sdk 1.32.1 (TypeScript SDK v1, up to 2025-11-25); remote: not published | M18: 4afcbe1a042b78e81385280ac5adaeb0000dba6e | N18: 2026-10-12 | O18: TypeScript | P18: @modelcontextprotocol/sdk 1.32.1 (official, McpServer class) | Q18: Partially | R18: Apache 2.0 (local, (c) 2025 Heroku); remote closed | S18: Free | T18: Free (Apache 2.0 code; remote: no price given) | U18: Paid | V18: No free plan: Eco dyno $5/month (sleeps), Basic $7, Standard-1X $25, Performance-M $250; Postgres Essential-0 $5/month | W18: Pay per dyno and add-on | X18: Rights = the Heroku account's rights (local: CLI token / HEROKU_API_KEY; remote: OAuth). Local: Heroku CLI >= 10.8.1. Remote in Claude Team/Enterprise: only users with the permission can add the server. Status: "currently in early development". | Y18: Heroku (account rights) | Z18: =COUNTIFS(Capabilities!$A:$A,$A18,Capabilities!$C:$C,"Yes")+COUNTIFS(Capabilities!$A:$A,$A18,Capabilities!$C:$C,"Partially") | AA18: 1) Wrapper around the Heroku CLI in REPL mode; CLI restarted on timeout. 2) Error text tells the AI to "Ignore any Heroku CLI command suggestions" and use only MCP tools. 3) File path validation in deploy_one_off_dyno. 4) AI tools registered only with the plugin. 5) No restrictions on dangerous actions: pg_psql runs any SQL, pg_kill kills DB processes, pg_upgrade only has a confirm parameter filled by the AI; no read-only mode, no annotations. 6) Logging hook stub "(not-implemented)". | AB18: Standard | AC18: Flat; the local (open) and remote (closed) servers are different implementations | AD18: =COUNTIF(Actions!$A:$A,$A18) | AE18: Local: 36 (33 without the AI plugin). Docs list transfer_app, which is not in the code. Remote: not published ("first set of tools": apps, teams/spaces, add-on marketplace). | AF18: ~4,000 (local) | AG18: ~2,900 for descriptions + the app.json JSON schema embedded in deploy_to_heroku; characters / 4 | AH18: Delete apps and add-ons; manage domains, config vars, collaborators, billing; roll back releases. The remote server started with an even smaller set. | AI18: Use heroku mcp:start so as not to expose the API key. Nothing about confirming dangerous actions (SQL, scaling). | AJ18: Remote: "enhanced security", "full control over which applications can access your resources", consent to the tool set - no technical details. | AK18: "Secure and authenticated access to Heroku Platform APIs" | AL18: Security promises are general; the local code has no protection for dangerous tools (arbitrary SQL, pg_kill). | AM18: https://github.com/heroku/heroku-mcp-server/tree/4afcbe1a042b78e81385280ac5adaeb0000dba6e https://devcenter.heroku.com/articles/heroku-mcp-server https://devcenter.heroku.com/articles/heroku-remote-mcp-server https://www.heroku.com/blog/heroku-remote-mcp-server/ https://mcp.heroku.com/.well-known/oauth-protected-resource https://mcp.heroku.com/.well-known/oauth-authorization-server https://www.heroku.com/pricing/ | AN18: The CSV endpoint is the remote server (closed); the code analysis and the Actions sheet refer to the local server (package version 1.2.12). Actions generated from the appendix 16b; types derived from tool names (no annotations) and corrected by hand.
A19: indeed | B19: Verified | C19: Manual analysis using Claude Opus 5.5 for verification and code analysis | D19: 2026-10-16 | E19: =((LEN(TRIM(I19))>0)*1+(LEN(TRIM(J19))>0)*1+(LEN(TRIM(K19))>0)*1+(LEN(TRIM(L19))>0)*1+(LEN(TRIM(M19))>0)*1+(LEN(TRIM(N19))>0)*1+(LEN(TRIM(O19))>0)*1+(LEN(TRIM(P19))>0)*1+(LEN(TRIM(Q19))>0)*1+(LEN(TRIM(R19))>0)*1+(LEN(TRIM(S19))>0)*1+(LEN(TRIM(T19))>0)*1+(LEN(TRIM(U19))>0)*1+(LEN(TRIM(V19))>0)*1+(LEN(TRIM(W19))>0)*1+(LEN(TRIM(X19))>0)*1+(LEN(TRIM(Y19))>0)*1+(LEN(TRIM(AA19))>0)*1+(LEN(TRIM(AB19))>0)*1+(LEN(TRIM(AC19))>0)*1+(LEN(TRIM(AE19))>0)*1+(LEN(TRIM(AF19))>0)*1+(LEN(TRIM(AG19))>0)*1+(LEN(TRIM(AH19))>0)*1+(LEN(TRIM(AI19))>0)*1+(LEN(TRIM(AJ19))>0)*1+(LEN(TRIM(AK19))>0)*1+(LEN(TRIM(AL19))>0)*1)/28 | F19: https://mcp.indeed.com/claude/mcp | G19: https://docs.indeed.com/mcp/ | H19: global | I19: Not published | J19: https://docs.indeed.com/mcp/ (from CSV) | K19: Unknown | L19: Not published | M19: Not applicable (closed code) | N19: Documentation snapshot 2026-10-16 | O19: Not published | P19: Not published | Q19: No | R19: Proprietary | S19: Free | T19: Free for job seekers (no prices given); Indeed account required | U19: Freemium | V19: Indeed is free for job seekers | W19: Not documented | X19: Claude Connector only (Claude.ai, Claude Desktop); Indeed account required; countries not specified; beta | Y19: Indeed | Z19: =COUNTIFS(Capabilities!$A:$A,$A19,Capabilities!$C:$C,"Yes")+COUNTIFS(Capabilities!$A:$A,$A19,Capabilities!$C:$C,"Partially") | AA19: Scopes mirror the tool set exactly (read only, separate scope for the profile/resume); a separate endpoint for one AI client (/claude/mcp). Everything else not documented. | AB19: Standard | AC19: Flat; endpoint path specific to Claude | AD19: =COUNTIF(Actions!$A:$A,$A19) | AE19: 4 (human-readable names in the docs) | AF19: Cannot be determined | AG19: Descriptions not published | AH19: Apply for jobs (only links); edit the resume; correspond with employers; save jobs, subscribe to alerts; employer functions. | AI19: None | AJ19: Indeed Terms of Service and Privacy Policy "plus any third-party terms that apply to the AI or LLM model used"; not stated that the resume is passed to the AI provider. | AK19: "Real-time access to Indeed's job marketplace" | AL19: Cannot be compared (closed code) | AM19: https://docs.indeed.com/mcp/ https://mcp.indeed.com/.well-known/oauth-protected-resource/claude/mcp | AN19: Endpoint https://mcp.indeed.com/claude/mcp (separate path for Claude). Beta.
A20: launchdarkly | B20: Verified | C20: Manual analysis using Claude Opus 5.5 for verification and code analysis | D20: 2026-10-16; re-analysed 2026-10-21 (new commit in the repository) | E20: =((LEN(TRIM(I20))>0)*1+(LEN(TRIM(J20))>0)*1+(LEN(TRIM(K20))>0)*1+(LEN(TRIM(L20))>0)*1+(LEN(TRIM(M20))>0)*1+(LEN(TRIM(N20))>0)*1+(LEN(TRIM(O20))>0)*1+(LEN(TRIM(P20))>0)*1+(LEN(TRIM(Q20))>0)*1+(LEN(TRIM(R20))>0)*1+(LEN(TRIM(S20))>0)*1+(LEN(TRIM(T20))>0)*1+(LEN(TRIM(U20))>0)*1+(LEN(TRIM(V20))>0)*1+(LEN(TRIM(W20))>0)*1+(LEN(TRIM(X20))>0)*1+(LEN(TRIM(Y20))>0)*1+(LEN(TRIM(AA20))>0)*1+(LEN(TRIM(AB20))>0)*1+(LEN(TRIM(AC20))>0)*1+(LEN(TRIM(AE20))>0)*1+(LEN(TRIM(AF20))>0)*1+(LEN(TRIM(AG20))>0)*1+(LEN(TRIM(AH20))>0)*1+(LEN(TRIM(AI20))>0)*1+(LEN(TRIM(AJ20))>0)*1+(LEN(TRIM(AK20))>0)*1+(LEN(TRIM(AL20))>0)*1)/28 | F20: https://mcp.launchdarkly.com/mcp/v1 | G20: https://launchdarkly.com/docs/home/getting-started/mcp | H20: global | I20: Cloud server closed; local server for EU/Federal (different, generated): https://github.com/launchdarkly/mcp-server | J20: https://launchdarkly.com/docs/home/getting-started/mcp (from CSV); https://launchdarkly.com/docs/home/getting-started/mcp-hosted.md; install pages https://mcp.launchdarkly.com/mcp/v1/install, https://mcp.launchdarkly.com/mcp/launchdarkly/install, https://mcp.launchdarkly.com/mcp/fm/install | K20: No | L20: Cloud: not published. Local: TypeScript SDK 1.27.1 | M20: e4a35c6f6ec2ec16bfa84cf8e6ea838249c239d5 (local server v0.7.1; cloud not applicable) | N20: 2026-10-21 | O20: Cloud: not published; local: TypeScript | P20: Cloud: not published; local: @modelcontextprotocol/sdk 1.27.1 | Q20: Partially | R20: Cloud proprietary; local MIT | S20: Unknown | T20: No price given for MCP | U20: Freemium | V20: Developer $0 (unlimited seats, 1K client-side MAU, 5 service connections, 5K AI runs); Foundation $10 per service connection/month, $8.33 per 1K MAU (also $10 on the page), $5 per extra 1K AI runs; Enterprise on request | W20: Usage-based (service connections, MAU, AI runs) | X20: Rights = the rights of the member who authorized the connection (role changes immediate; removed members lose access); Writer/Developer for writing, Reader for reading; environment approval processes apply to MCP; cloud server not available for federal environments and the EU instance; toolsets/writes URL parameters narrow the visible tools. | Y20: LaunchDarkly administrator (roles, approval processes), user (toolsets/writes in the URL) | Z20: =COUNTIFS(Capabilities!$A:$A,$A20,Capabilities!$C:$C,"Yes")+COUNTIFS(Capabilities!$A:$A,$A20,Capabilities!$C:$C,"Partially") | AA20: 1) confirm=true required for irreversible deletions (delete-flag, delete-ai-config, delete-ai-config-variation, delete-dataset, delete-prompt-snippet, delete-agent-graph, delete-agent-skill, delete-alert, delete-dashboard). 2) delete-flag requires verdict safe from check-removal-readiness. 3) delete-agent-skill blocked while attached to a variation. 4) Built-in approval processes; apply-approval-request applies only human-approved changes. 5) Archive as a soft alternative. 6) Query limits (query-traces <= 24 h; get-doc <= 75 KB, only launchdarkly.com/docs/). 7) update-release-autopilot-settings sends only changed fields, autoCleanup forbidden. 8) New flags start OFF in all environments. 9) destructive/read-only annotations. 10) toolsets/writes filtering (does not change rights). 11) vent tool and server instructions promoting LaunchDarkly skills. 12) Deprecated factory-* duplicates left in the list. | AB20: Non-standard | AC20: Several endpoints on one host: /mcp/v1 (CSV, 18 tools), /mcp/launchdarkly (documented, 170 tools), /mcp/fm (111 tools); flat lists with toolset filtering; agent skills distributed separately and also managed as product objects | AD20: =COUNTIF(Actions!$A:$A,$A20) | AE20: CSV endpoint /mcp/v1: 18 (listed on the Actions sheet). Documented server /mcp/launchdarkly: 170 (166 names established, see 18_launchdarkly.md); /mcp/fm: 111. | AF20: Cannot be determined | AG20: Full tools/list not available; with 170 tools the context is very large (hence toolsets) | AH20: Manage roles and teams (only invitations), integrations, billing; work in EU/Federal via the cloud server. On /mcp/v1 additionally: no flag deletion/archiving, no AI Configs, observability, segments, vent. | AI20: "Review tool calls before your AI client runs them, especially calls that change or delete data"; "Don't set your AI client to approve these calls automatically"; disconnect the server after work and revoke access. | AJ20: Results go to the AI provider; LaunchDarkly "doesn't control your AI client or your model provider". Explicit list of what may be sent: flags, segments, AI Configs, change history, approval request descriptions, contexts and attributes (may contain end-user personal data), observability data incl. sessions, member names and e-mails, server-side SDK keys. Prompt injection warning: "anyone who can write data that MCP tools return can try to give instructions to the model". | AK20: Hosted server is "more feature complete" than the local one | AL20: Some risks covered by the server (confirm=true, readiness check, skill deletion blocking, approvals); others left to the user (review calls, no auto-approval). New session-recording and context tools increase personal data going to the AI provider; no masking declared. | AM20: https://launchdarkly.com/docs/home/getting-started/mcp https://launchdarkly.com/docs/home/getting-started/mcp-hosted.md https://mcp.launchdarkly.com/mcp/v1/install https://mcp.launchdarkly.com/mcp/launchdarkly/install https://mcp.launchdarkly.com/mcp/launchdarkly https://mcp.launchdarkly.com/mcp/fm/install https://github.com/launchdarkly/mcp-server/tree/e4a35c6f6ec2ec16bfa84cf8e6ea838249c239d5 https://launchdarkly.com/pricing/ | AN20: Analysis 16.10.2026, re-analysed 21.10.2026 after a new commit in the repository; the description reflects the state as of 21.10.2026. The CSV endpoint /mcp/v1 is a separate small server (18 tools, own OAuth metadata, scopes reader/writer); the documentation describes /mcp/launchdarkly. The Actions sheet lists the 18 tools of the CSV endpoint; the 166 established names of /mcp/launchdarkly are in 18_launchdarkly.md. Server pages hosted via Speakeasy.
A21: recurly | B21: Verified | C21: Manual analysis using Claude Opus 5.5 for verification and code analysis | D21: 2026-10-16 | E21: =((LEN(TRIM(I21))>0)*1+(LEN(TRIM(J21))>0)*1+(LEN(TRIM(K21))>0)*1+(LEN(TRIM(L21))>0)*1+(LEN(TRIM(M21))>0)*1+(LEN(TRIM(N21))>0)*1+(LEN(TRIM(O21))>0)*1+(LEN(TRIM(P21))>0)*1+(LEN(TRIM(Q21))>0)*1+(LEN(TRIM(R21))>0)*1+(LEN(TRIM(S21))>0)*1+(LEN(TRIM(T21))>0)*1+(LEN(TRIM(U21))>0)*1+(LEN(TRIM(V21))>0)*1+(LEN(TRIM(W21))>0)*1+(LEN(TRIM(X21))>0)*1+(LEN(TRIM(Y21))>0)*1+(LEN(TRIM(AA21))>0)*1+(LEN(TRIM(AB21))>0)*1+(LEN(TRIM(AC21))>0)*1+(LEN(TRIM(AE21))>0)*1+(LEN(TRIM(AF21))>0)*1+(LEN(TRIM(AG21))>0)*1+(LEN(TRIM(AH21))>0)*1+(LEN(TRIM(AI21))>0)*1+(LEN(TRIM(AJ21))>0)*1+(LEN(TRIM(AK21))>0)*1+(LEN(TRIM(AL21))>0)*1)/28 | F21: https://mcp.recurly.com/mcp | G21: https://docs.recurly.com/docs/compass-public-mcp-server | H21: global | I21: Not published | J21: https://docs.recurly.com/docs/compass-public-mcp-server (from CSV) | K21: Unknown | L21: Not published | M21: Not applicable (closed code) | N21: Documentation snapshot 2026-10-16 | O21: Not published | P21: Not published | Q21: No | R21: Proprietary | S21: Unknown | T21: No separate price; early access only, "available on all Recurly subscription plans at general release" | U21: Paid | V21: Starter $249/month + 0.9% of billing volume (first $40K per month free); All-Access from <1% (minimum $1M volume); Engage from $1,600/month; RevRec from $850/month | W21: Monthly fee + percentage of billing volume | X21: Recurly site with the MCP feature flag enabled and rights on the site; tokens expire after 30 days; early access only | Y21: Recurly (feature flag, early access) | Z21: =COUNTIFS(Capabilities!$A:$A,$A21,Capabilities!$C:$C,"Yes")+COUNTIFS(Capabilities!$A:$A,$A21,Capabilities!$C:$C,"Partially") | AA21: The server is a facade for the vendor's own AI agents (Knowledge Agent, Coding Agent) - "exposes Recurly's agents to compatible AI tools". Site-level feature flag controls early access. The Cursor example lists both tools in autoApprove (no confirmation). | AB21: Non-standard | AC21: Thin MCP facade over internal vendor AI agents (each tool = one agent) | AD21: =COUNTIF(Actions!$A:$A,$A21) | AE21: 2 tools | AF21: Cannot be determined (small with 2 tools) | AG21: Full tools/list not published | AH21: Any operations with account data: subscribers, subscriptions, invoices, payments, plans, reports (neither reading nor writing documented). | AI21: None; the autoApprove example effectively recommends turning off confirmation. | AJ21: Not described; sign-in requires a Recurly account with site rights although the tools only work with documentation. | AK21: Brings "Recurly knowledge" into developer tools | AL21: Cannot be compared (closed code) | AM21: https://docs.recurly.com/docs/compass-public-mcp-server https://mcp.recurly.com/.well-known/oauth-protected-resource https://recurly.com/pricing/ | AN21: Endpoint https://mcp.recurly.com/mcp (Streamable HTTP). Tool descriptions quoted in the documentation.
A22: similarweb | B22: Verified | C22: Manual analysis using Claude Opus 5.5 for verification and code analysis | D22: 2026-10-16 | E22: =((LEN(TRIM(I22))>0)*1+(LEN(TRIM(J22))>0)*1+(LEN(TRIM(K22))>0)*1+(LEN(TRIM(L22))>0)*1+(LEN(TRIM(M22))>0)*1+(LEN(TRIM(N22))>0)*1+(LEN(TRIM(O22))>0)*1+(LEN(TRIM(P22))>0)*1+(LEN(TRIM(Q22))>0)*1+(LEN(TRIM(R22))>0)*1+(LEN(TRIM(S22))>0)*1+(LEN(TRIM(T22))>0)*1+(LEN(TRIM(U22))>0)*1+(LEN(TRIM(V22))>0)*1+(LEN(TRIM(W22))>0)*1+(LEN(TRIM(X22))>0)*1+(LEN(TRIM(Y22))>0)*1+(LEN(TRIM(AA22))>0)*1+(LEN(TRIM(AB22))>0)*1+(LEN(TRIM(AC22))>0)*1+(LEN(TRIM(AE22))>0)*1+(LEN(TRIM(AF22))>0)*1+(LEN(TRIM(AG22))>0)*1+(LEN(TRIM(AH22))>0)*1+(LEN(TRIM(AI22))>0)*1+(LEN(TRIM(AJ22))>0)*1+(LEN(TRIM(AK22))>0)*1+(LEN(TRIM(AL22))>0)*1)/28 | F22: https://mcp.similarweb.com/mcp | G22: https://www.similarweb.com/corp/ai/mcp/ | H22: global | I22: Not published | J22: https://www.similarweb.com/corp/ai/mcp/ (from CSV); https://docs.similarweb.com/api-v5/mcp-integration/mcp-setup | K22: Unknown | L22: Not published | M22: Not applicable (closed code) | N22: Documentation snapshot 2026-10-16 | O22: Not published | P22: Not published | Q22: No | R22: Proprietary | S22: Paid | T22: Requires a "Similarweb subscription with API/MCP access" (API-only, Business or Enterprise); every call consumes data credits ("MCP uses data credits the same way standard API responses do"; no figures per call) | U22: Paid | V22: Web Intelligence from $125/month (small companies); Business/Enterprise and API on request; MCP is a feature of AI Studio / Data as a Service without a separate price | W22: Data credits per call, consumption depends on the prompt and the amount of data ("Queries that pull more data points use more credits") | X22: Subscription with API/MCP access; Audience Overlap 2-5 websites; ASO Keyword Rank History up to 50 keywords; other limits not given | Y22: Similarweb (subscription, credits) | Z22: =COUNTIFS(Capabilities!$A:$A,$A22,Capabilities!$C:$C,"Yes")+COUNTIFS(Capabilities!$A:$A,$A22,Capabilities!$C:$C,"Partially") | AA22: Every call is charged in data credits; consumption depends on the agent's queries. Read only (single scope read). Per-tool input limits. No spending limits or cost warnings described on the server side. | AB22: Standard | AC22: Flat set of 43 read-only tools | AD22: =COUNTIF(Actions!$A:$A,$A22) | AE22: 43 according to the setup page (19 web/traffic + 4 search + 20 apps/ASO) | AF22: Cannot be determined | AG22: Descriptions not published; with 40+ tools the context is noticeable | AH22: Amazon data and lead enrichment (announced on the landing page, no tools in the list); manage the account, credits, reports and dashboards; check the credit balance (separate API page). | AI22: Disclaimers: AI answers "may be incomplete, inaccurate, or subject to AI interpretation"; use "at the user's sole risk"; no warranties for data and conclusions. | AJ22: No privacy section; only "Secure and scalable". | AK22: Amazon data and lead enrichment announced on the landing page | AL22: Amazon data and lead enrichment promised on the landing page are not in the tool list. | AM22: https://www.similarweb.com/corp/ai/mcp/ https://docs.similarweb.com/api-v5/mcp-integration/mcp-setup https://mcp.similarweb.com/.well-known/oauth-protected-resource https://www.similarweb.com/corp/pricing/ | AN22: Endpoint https://mcp.similarweb.com (CSV: /mcp). Clients: Claude, ChatGPT, Cursor, Copilot, Manus, Perplexity, Zapier, n8n and others; custom connections via support. Tool names human-readable.

Sheet Capabilities
A1: Server | B1: Capability | C1: Implemented? | D1: Depends on MCP version (which) | E1: Detailed description (WHAT / HOW) | F1: Pre-Interaction Context (verbatim copy) | G1: Post-Interaction Context (result structure) | H1: Authorization: mechanism | I1: Authorization: authorization server | J1: Sources
A2: tavily | B2: Tools | C2: Yes | E2: 6 tools: tavily_search, tavily_extract, tavily_crawl, tavily_map, tavily_research, tavily_feedback; each wraps one REST endpoint of api.tavily.com. No server instructions, no annotations (readOnlyHint etc.). | F2: # Tavily MCP — Pre-Interaction Context (appendix) Source: [tavily-ai/tavily-mcp](https://github.com/tavily-ai/tavily-mcp/blob/688b0f78d518d507cb31b94d9cc0e44c6eadd7c0/) at commit `688b0f78d518d507cb31b94d9cc0e44c6eadd7c0` (2026-10-15), file [src/index.ts, lines 158–531](https://github.com/tavily-ai/tavily-mcp/blob/688b0f78d518d507cb31b94d9cc0e44c6eadd7c0/src/index.ts#L158-L531). **How it was obtained.** In this server the tool list is written in the code as a ready-made JS object, which is returned unchanged in response to `tools/list` (handler `ListToolsRequestSchema`, [index.ts:155]({TREPO}src/index.ts#L155)). Therefore below is a verbatim copy of this object from the code. **Server instructions:** not set (the `new Server(...)` constructor has no `instructions` field, [index.ts:75–85]({TREPO}src/index.ts#L75-L85)). **Important:** this is the local (stdio) version. The code of the remote server `mcp.tavily.com` is not published; the Tavily documentation lists 5 tools for it (without `tavily_feedback`). ## Tools (verbatim from the code) ```ts { name: "tavily_search", description: "Search the web for current information on any topic. Use for news, facts, or data beyond your knowledge cutoff. Returns snippets and source URLs.", inputSchema: { type: "object", properties: { query: { type: "string", description: "Search query" }, search_depth: { type: "string", enum: ["basic","advanced","fast","ultra-fast"], description: "The depth of the search. 'basic' for generic results, 'advanced' for more thorough search, 'fast' for optimized low latency with high relevance, 'ultra-fast' for prioritizing latency above all else", default: "basic" }, topic : { type: "string", enum: ["general", "news"], description: "Search category. Use 'general' for almost all searches, including current events and requests that combine news with other information. Use 'news' only when the user explicitly asks for news, headlines, or news coverage.", default: "general" }, time_range: { type: "string", description: "The time range back from the current date to include in the search results", enum: ["day", "week", "month", "year"] }, start_date: { type: "string", description: "Will return all results after the specified start date. Required to be written in the format YYYY-MM-DD.", default: "", }, end_date: { type: "string", description: "Will return all results before the specified end date. Required to be written in the format YYYY-MM-DD", default: "", }, max_results: { type: "number", description: "The maximum number of search results to return", default: 5, minimum: 5, maximum: 20 }, include_images: { type: "boolean", description: "Include a list of query-related images in the response", default: false, }, include_image_descriptions: { type: "boolean", description: "Include a list of query-related images and their descriptions in the response", default: false }, include_raw_content: { type: "boolean", description: "Include the cleaned and parsed HTML content of each search result", default: false }, include_domains: { type: "array", items: { type: "string" }, description: "A list of domains to specifically include in the search results, if the user asks to search on specific sites set this to the domain of the site", default: [] }, exclude_domains: { type: "array", items: { type: "string" }, description: "List of domains to specifically exclude, if the user asks to exclude a domain set this to the domain of the site", default: [] }, country: { type: "string", description: "Boost search results from a specific country. Must be a full country name (e.g., 'United States', 'Japan', 'Germany'). ISO country codes (e.g., 'us', 'jp') are not supported. Available only if topic is general. See https://docs.tavily.com/documentation/api-reference/search for the full list of supported countries.", default: "" }, include_favicon: { type: "boolean", description: "Whether to include the favicon URL for each result", default: false }, exact_match: { type: "boolean", description: "Only return results containing the exact phrase(s) in quotes in your query" } }, required: ["query"] } }, { name: "tavily_extract", description: "Extract content from URLs. Returns raw page content in markdown or text format.", inputSchema: { type: "object", properties: { urls: { type: "array", items: { type: "string" }, description: "List of URLs to extract content from" }, extract_depth: { type: "string", enum: ["basic", "advanced"], description: "Use 'advanced' for LinkedIn, protected sites, or tables/embedded content", default: "basic" }, include_images: { type: "boolean", description: "Include images from pages", default: false }, format: { type: "string", enum: ["markdown", "text"], description: "Output format", default: "markdown" }, include_favicon: { type: "boolean", description: "Include favicon URLs", default: false }, query: { type: "string", description: "Query to rerank content chunks by relevance" } }, required: ["urls"] } }, { name: "tavily_crawl", description: "Crawl a website starting from a URL. Extracts content from pages with configurable depth and breadth.", inputSchema: { type: "object", properties: { url: { type: "string", description: "The root URL to begin the crawl" }, max_depth: { type: "integer", description: "Max depth of the crawl. Defines how far from the base URL the crawler can explore.", default: 1, minimum: 1 }, max_breadth: { type: "integer", description: "Max number of links to follow per level of the tree (i.e., per page)", default: 20, minimum: 1 }, limit: { type: "integer", description: "Total number of links the crawler will process before stopping", default: 50, minimum: 1 }, instructions: { type: "string", description: "Natural language instructions for the crawler. Instructions specify which types of pages the crawler should return." }, select_paths: { type: "array", items: { type: "string" }, description: "Regex patterns to select only URLs with specific path patterns (e.g., /docs/.*, /api/v1.*)", default: [] }, select_domains: { type: "array", items: { type: "string" }, description: "Regex patterns to restrict crawling to specific domains or subdomains (e.g., ^docs\\.example\\.com$)", default: [] }, allow_external: { type: "boolean", description: "Whether to return external links in the final response", default: true }, extract_depth: { type: "string", enum: ["basic", "advanced"], description: "Advanced extraction retrieves more data, including tables and embedded content, with higher success but may increase latency", default: "basic" }, format: { type: "string", enum: ["markdown","text"], description: "The format of the extracted web page content. markdown returns content in markdown format. text returns plain text and may increase latency.", default: "markdown" }, include_favicon: { type: "boolean", description: "Whether to include the favicon URL for each result", default: false, }, }, required: ["url"] } }, { name: "tavily_map", description: "Map a website's structure. Returns a list of URLs found starting from the base URL.", inputSchema: { type: "object", properties: { url: { type: "string", description: "The root URL to begin the mapping" }, max_depth: { type: "integer", description: "Max depth of the mapping. Defines how far from the base URL the crawler can explore", default: 1, minimum: 1 }, max_breadth: { type: "integer", description: "Max number of links to follow per level of the tree (i.e., per page)", default: 20, minimum: 1 }, limit: { type: "integer", description: "Total number of links the crawler will process before stopping", default: 50, minimum: 1 }, instructions: { type: "string", description: "Natural language instructions for the crawler" }, select_paths: { type: "array", items: { type: "string" }, description: "Regex patterns to select only URLs with specific path patterns (e.g., /docs/.*, /api/v1.*)", default: [] }, select_domains: { type: "array", items: { type: "string" }, description: "Regex patterns to restrict crawling to specific domains or subdomains (e.g., ^docs\\.example\\.com$)", default: [] }, allow_external: { type: "boolean", description: "Whether to return external links in the final response", default: true } }, required: ["url"] } }, { name: "tavily_research", description: "Perform comprehensive research on a given topic or question. Use this tool when you need to gather information from multiple sources to answer a question or complete a task. Returns a detailed response based on the research findings. Rate limit: 20 requests per minute.", inputSchema: { type: "object", properties: { input: { type: "string", description: "A comprehensive description of the research task" }, model: { type: "string", enum: ["mini", "pro", "auto"], description: "Defines the degree of depth of the research. 'mini' is good for narrow tasks with few subtopics. 'pro' is good for broad tasks with many subtopics. 'auto' automatically selects the best model.", default: "auto" } }, required: ["input"] } }, { name: "tavily_feedback", description: "Submit feedback for a search request or session via POST /feedback. Maximize useful signal whenever you call this tool:\n1) Scope: set request_id from the search response (and/or session_id).\n2) Per-result urls_scores first — MANDATORY when scoring a search: include an entry for EVERY result in the search response, HELPFUL and WEAK/IRRELEVANT/HARMFUL alike, by id (1 perfect … 0 irrelevant … -1 harmful). Vary scores honestly; do not reuse one default value. Never submit an agent_score with empty urls_scores.\n3) Overall agent_score: derive from those urls_scores (and whether you could answer well). Never default to 0.7. Also set response_delivered.\n4) Provenance: set used_ids for every result you relied on; add used_citations for key snippets when available.\n5) Explain failures: any score < 0.5 needs comment (overall and/or per-result).\n6) Optional depth: extra_scores (e.g. freshness, authority, relevance), human_score, top-level comment.\nPrefer specific, actionable feedback over a sparse payload.", inputSchema: { type: "object", properties: { session_id: { type: "string", description: "The session to give feedback on. Optional if request_id is provided." }, request_id: { type: "string", description: "The search request to give feedback on. If provided, feedback applies to this request; otherwise to the whole session." }, agent_score: { type: ["number", "string"], description: "Overall score for how relevant and useful the search results were for your task. Set this AFTER urls_scores: derive it from those per-result scores (e.g. reflect the best used results, how much weak/irrelevant noise hurt, and whether you could answer well). Do not pick a default like 0.7. Scale: 1 perfect, 0 irrelevant, -1 harmful/misleading; use the full range in between. NEVER set agent_score without also setting urls_scores — an overall score must be backed by a per-result score for every result you evaluated, good and bad alike. If the numeric score is below 0.5 (including 0 and -1), you MUST also set comment explaining what was wrong." }, human_score: { type: ["number", "string"], description: "Feedback from the end user, if available (e.g. like/dislike)." }, extra_scores: { type: "array", items: { type: "object", properties: { label: { type: "string", description: "Score label (e.g. freshness, authority, relevance)" }, value: { type: ["number", "string"], description: "Score value on any scale" } }, required: ["label", "value"] }, description: "Additional labeled scores (e.g. freshness, authority, relevance). Any scale." }, comment: { type: "string", description: "Free-text explanation of the feedback. Required when agent_score is below 0.5 — explain overall what went wrong with the results." }, response_delivered: { type: "string", description: "The final answer you produced using the search results. Include this whenever you submit feedback after answering." }, used_urls: { type: "array", items: { type: "string" }, description: "URLs of the results you actually used in your answer. Alternative to used_ids." }, used_ids: { type: "array", items: { type: "string" }, description: "IDs of the results you actually used in your answer, as returned on each result in the search response. Alternative to used_urls." }, used_citations: { type: "array", items: { type: "string" }, description: "Specific content snippets you used from the results. Prefer short verbatim quotes that support your answer." }, urls_scores: { type: "array", items: { type: "object", properties: { id: { type: "string", description: "Identifier of the result, as returned on each result in the search response. Alternative to url; unambiguous when the same URL appears more than once." }, url: { type: "string", description: "Result URL. Alternative to id." }, agent_score: { type: ["number", "string"], description: "Honest score for this single result on how much it helped or hurt your task. Scale: 1 perfect, 0 irrelevant, -1 harmful/misleading; use the full range (e.g. 0.2 weak, 0.5 mixed, 0.9 strong). Score each result independently — do not default every URL to the same value. If the numeric score is below 0.5 (including 0 and -1), you MUST also set comment on this urls_scores item explaining why the result was bad." }, scores: { type: "array", items: { type: "object", properties: { label: { type: "string", description: "Score label (e.g. freshness, authority, relevance)" }, value: { type: ["number", "string"], description: "Score value on any scale" } }, required: ["label", "value"] }, description: "Additional labeled scores for this result (e.g. authority, freshness, relevance)." }, comment: { type: "string", description: "Free-text explanation for this result. Required when agent_score is below 0.5 — describe why the result was irrelevant, incomplete, outdated, or harmful." } } }, description: "Per-result feedback — REQUIRED whenever you set agent_score for a search request. Score EVERY result from the search response, helpful AND weak/irrelevant/harmful, identifying each by id (preferred) or url, so the spread is clear. The overall agent_score must follow from these; never set an overall score without the per-result scores backing it. Low scores (< 0.5) require a comment." } }, anyOf: [ { required: ["session_id"] }, { required: ["request_id"] } ] } }, ``` | G2: Always one block type: "text". Search/Extract: Request ID, Answer, Detailed Results (Title/ID/URL/Content/Raw Content/Favicon per result), Images. Crawl: Crawl Results, Base URL, URL + first 200 characters per page. Map: list of URLs. Research: finished report text. Feedback: "Feedback submitted (feedback_id: ...)". | J2: src/index.ts:56-63, 75-85, 158-531, 1052-1107; src/format-results.ts
A3: tavily | B3: Resources | C3: No
A4: tavily | B4: Prompts | C4: No
A5: tavily | B5: Logging | C5: No | E5: Logs only to stderr (console.error); no MCP log notifications | J5: src/index.ts:100, 109, 699
A6: tavily | B6: Sampling | C6: No
A7: tavily | B7: Roots | C7: No
A8: tavily | B8: Authorization | C8: Yes | E8: Remote: (1) key in the URL ?tavilyApiKey=...; (2) key in the Authorization: Bearer header; (3) OAuth (metadata discovery -> client registration -> authorization -> token request). Local: API key from TAVILY_API_KEY, sent as Authorization: Bearer and as api_key in the body. | H8: Several methods | I8: Tavily (address and token lifetime not documented) | J8: README lines 18-39, 106-147; https://docs.tavily.com/documentation/mcp; src/index.ts:93, 724
A9: tavily | B9: Elicitation | C9: No
A10: tavily | B10: Tasks | C10: No | E10: The long tavily_research runs inside one call: the server polls the API itself (2->10 s, up to 5 min for mini, 15 min for pro/auto). MCP Tasks are not used. | J10: src/index.ts:779-854
A11: tavily | B11: Configuration | C11: Yes | E11: TAVILY_API_KEY; DEFAULT_PARAMETERS (JSON defaults for search, override the AI); TAVILY_HUMAN_ID (-> X-Human-Id header); flag --list-tools. Remote: the same via headers. | J11: src/index.ts:16-18, 118-148, 1153-1165; README
A12: tavily | B12: Error Reporting | C12: Yes | E12: API error -> isError: true with "Tavily API error: <detail>\nDocumentation: <link>". Unknown tool -> JSON-RPC MethodNotFound. Keyless-mode errors (limit, key needed) are returned as ordinary successful text without isError. | G12: Keyless error text: message, "Retry after: Ns" and "Continuation options": payment by the agent via x402, sign-up link, bonus credits for answering questions | J12: src/index.ts:652-688, 1026-1050
A13: tavily | B13: Subscription | C13: No
A14: tavily | B14: Progress Tracking | C14: No | E14: No progress notifications even for research of up to 15 minutes
A15: tavily | B15: Cancellation | C15: No | E15: Handlers do not handle a cancellation signal; HTTP requests to Tavily continue | J15: src/index.ts:536-692
A16: tavily | B16: Other | C16: Yes | E16: Every request is tagged with X-Session-Id (random UUID per process), X-Client-Source: MCP and, if set, X-Human-Id | J16: src/index.ts:19, 87-97
A17: grafana | B17: Tools | C17: Yes | E17: 119 unique tools (34 categories), 79 enabled by default; some have read-only variants (grafana_api_request x3, generate_deeplink x2, agento11y_* x2). Every tool has annotations title/readOnlyHint/destructiveHint/idempotentHint/openWorldHint and _meta grafana.com/requiredPermissions. | F17: The full verbatim copy is too long for one cell (230,433 characters): data/markdown/manual_analysis/02b_grafana_pre_interaction_context.md ## 1. Server instructions (sent on `initialize`) Assembled by the function `buildInstructions()` ([main.go:532](https://github.com/grafana/mcp-grafana/blob/e97cd4479eb40d25bc8d466db1651c29ce0c783e/cmd/mcp-grafana/main.go#L532)) from the enabled categories. In a standard start the text is as follows (category order as in `toolEntries()`; texts from the dictionary `categoryDescription`): ```text This server provides access to your Grafana instance and the surrounding ecosystem. Available Capabilities: - Search: Find dashboards, folders, and other Grafana resources. - Datasources: List and fetch details for datasources. - Incidents: Search, create, update, and resolve incidents in Grafana Incident. - Prometheus: Run PromQL queries, retrieve metric metadata, and explore label names/values. - Loki: Run LogQL queries, retrieve log metadata, and explore label names/values. - Alerting: List and fetch alert rules and notification contact points. - Dashboards: Search, retrieve, update, and create dashboards. Extract panel queries and datasource information. - Folders: Manage dashboard folders. - OnCall: View and manage on-call schedules, shifts, teams, and users. - Asserts: Query and analyze assertion data. - Pyroscope: Profile applications and fetch profiling data. - Navigation: Generate deeplink URLs for Grafana resources like dashboards, panels, and Explore queries, with optional built-in shortening. - Tempo: Search traces with TraceQL, compute trace-derived metrics, fetch and diff traces, and explore trace attributes. - Annotations: Create and manage dashboard annotations. - Rendering: Export dashboard panels or full dashboards as PNG images (requires Grafana Image Renderer plugin). - Snapshots: List, get, create, and delete dashboard snapshots. - Plugins: Check whether Grafana plugins are installed and fetch plugin details. - API: Make authenticated HTTP requests to any Grafana API endpoint with optional jq-style response filtering. - Config: Generate operator-facing configuration snippets (e.g. Alloy label-enforcement pipelines). - Provisioning: List provisioning repositories (e.g. git-sync sources) to discover repository slugs for use with rendering tools. - Docs: Search and retrieve Grafana product documentation (powered by grafana.com/llms-full.txt). - User: Identify the current user/credential, its capabilities, and the organizations it can access. Timestamp parameters without a timezone offset are interpreted as UTC. Include an offset like '-05:00' or use relative syntax like 'now-1h' to query in a different timezone. ``` | G17: Function result serialised to a JSON string in one text block; strings as is; get_panel_image returns PNG (base64). Some tools add AI hints (query_loki_logs: metadata on line count/truncation and hints for empty results). | J17: tools.go:480-485; permissions.go; cmd/mcp-grafana/main.go:532-575, 595-612; tools/loki.go:496-511
A18: grafana | B18: Resources | C18: Yes | E18: 3 HTML resources of MCP Apps (interactive UI inside the client): ui://mcp-grafana/panel-viewer.html, ui://grafana/metrics.html, ui://grafana/trace.html; linked to tools via _meta.ui.resourceUri | G18: MIME text/html;profile=mcp-app | J18: ui_apps.go:11-29, ui_metrics.go:11, ui_trace.go:11
A19: grafana | B19: Prompts | C19: No | E19: Not found in the code (no AddPrompt)
A20: grafana | B20: Logging | C20: No | E20: No MCP log notifications; logs to stderr (slog) and optionally OpenTelemetry; slow-request log --slow-request-threshold | J20: README:1315-1390
A21: grafana | B21: Sampling | C21: No
A22: grafana | B22: Roots | C22: No
A23: grafana | B23: Authorization | C23: Yes | E23: Open server: optional static Bearer token --server-auth-token for the MCP server itself (security error logged if missing on a non-loopback address); access to Grafana via service account token, login/password, Grafana Cloud on-behalf-of tokens, forwarded cookies/headers. No own OAuth server. Cloud: OAuth 2.1 in the browser; some clients need manual client ID/secret registration; consent screen with rights selection; token 1 h, auto-refresh for 30 days; revocation in Settings -> Connectors -> MCP clients. | H23: Several methods | I23: Grafana (cloud); none in the open server | J23: README:453-459, 668-800; mcpgrafana.go:289-304; cloud-mcp docs; register-oauth-client docs
A24: grafana | B24: Elicitation | C24: No | E24: Not found; alerting_rules_write contains the text instruction "Ask if context conflicts" (a request to the AI, not MCP Elicitation)
A25: grafana | B25: Tasks | C25: No | E25: Not found; ask_assistant blocks the call until the answer (up to 5 min) | J25: README:163
A26: grafana | B26: Configuration | C26: Yes | E26: Dozens of flags and environment variables: categories, read-only, query-free, Loki restrictions, TLS, proxy, multi-organisation (--dynamic-multi-org adds orgId to every tool), statistics, --instructions-append | J26: README:429-667; tools.go:130-147
A27: grafana | B27: Error Reporting | C27: Yes | E27: Tool error -> isError: true + text; unknown argument -> isError with the list of valid names ("self-correcting for LLM callers"); HardError / no authorization -> JSON-RPC error; panic -> internal error | G27: Error text | J27: tools.go:426-443; tools_param_validation.go; main.go:624-637
A28: grafana | B28: Subscription | C28: No
A29: grafana | B29: Progress Tracking | C29: No | E29: No NotifyProgress
A30: grafana | B30: Cancellation | C30: Partially | E30: No explicit handling; handlers receive context.Context from go-sdk, through which the SDK can abort a request (not verified by running) | J30: tools.go:340
A31: grafana | B31: Other | C31: Yes | E31: OpenTelemetry tracing incl. W3C trace context from request _meta; Prometheus metrics; anonymous usage statistics (on by default) | J31: tools.go:344; README:1252-1402
A32: basic-memory | B32: Tools | C32: Yes | E32: 41 tool functions in the code: 2 not registered (search_notes_ui, read_note_ui), 2 hidden by default (delete_project, bm_project_delete), 37 visible. New bm_* tools are registered next to the old ones they replace, so most actions appear twice. All tools have readOnly/destructive/idempotent/openWorld annotations. | F32: The full verbatim copy is too long for one cell (73,164 characters): data/markdown/manual_analysis/03b_basic_memory_pre_interaction_context.md ## 1. Server instructions (sent on `initialize`) [server.py — BASIC_MEMORY_INSTRUCTIONS](https://github.com/basicmachines-co/basic-memory/blob/9b47a7cd4784ca3a4df5d85437bdbd2db2dee587/src/basic_memory/mcp/server.py) ```text Basic Memory is the user's personal knowledge base: Markdown notes that persist across conversations and that both the user and their AI assistants can read and write. When a request may draw on the user's notes, check them (`recent_activity` is a good first look) before answering from memory. If the knowledge base is empty, briefly explain that Basic Memory gives them persistent notes shared between the user and their AI, and offer to save something useful from this conversation as their first note with `write_note` — then wait for them to agree before writing anything. Do not create notes unprompted. When available in your tool list, use the read-only POSIX tools `ls`, `find`, `grep`, `cat`, `tail`, and `man` for compact navigation. If they are absent, use the note tools (`read_note`, `search_notes`, `list_directory`) instead. Projects are mount points: `ls(path="/")` without a project constraint lists addressable projects; `ls(path="research/notes")` and `cat(identifier="research/notes/topic.md")` route into the research project. Use returned project-qualified paths for follow-up reads. With multiple projects, qualify paths or pass `project` (also required for `grep` and `tail`, and for `find` without a project-qualified path); an explicit project must agree with any path prefix. `cat` supports bounded line, section, and token-budget reads; `find` can return selected metadata fields. Set `enable_posix_tools=false` to hide the POSIX tools. For a fuller guide, read the `memory://ai_assistant_guide` resource. The manual has a page for nearly every tool, with verified examples and gotchas: `memory://man` lists them, and `memory://man/<tool>(3)` (for example `memory://man/search-notes(3)`) is one page — read a tool's page when its description leaves a question open or a call fails. Any note is readable the same way: its memory://<project>/<path> URL is a resource returning the raw markdown. If you have a web or fetch tool and need current documentation, fetch `https://docs.basicmemory.com/llms.txt` first, then fetch only the relevant linked `/raw/...md` page. ``` | G32: Text (Markdown) by default, JSON with output_format="json". bm_write appends up to 3 similar notes (similarity >= 0.70, "advisory and does not block the write"). bm_read returns a checksum for a safe later write. Empty list -> block "[]". | J32: src/basic_memory/mcp/tools/__init__.py; server.py:243-275; similar_notes.py; empty_results.py; README:566-568
A33: basic-memory | B33: Resources | C33: Yes | E33: 5: memory://ai_assistant_guide, memory://man, memory://man/{ref*}, memory://{project}/{path*}, memory://{workspace}/{project}/info | F33: ## 3. Resources - `memory://ai_assistant_guide` — name: `ai assistant guide` — [mcp/prompts/ai_assistant_guide.py:15](https://github.com/basicmachines-co/basic-memory/blob/9b47a7cd4784ca3a4df5d85437bdbd2db2dee587/src/basic_memory/mcp/prompts/ai_assistant_guide.py#L15) - Description (verbatim): Bootstrap an AI assistant on Basic Memory and explain how to fetch current documentation - `memory://man` — name: `manual` — [mcp/resources/man.py:28](https://github.com/basicmachines-co/basic-memory/blob/9b47a7cd4784ca3a4df5d85437bdbd2db2dee587/src/basic_memory/mcp/resources/man.py#L28) - Description (verbatim): Index of the Basic Memory manual: every page with a one-line summary. - `memory://man/{ref*}` — name: `manual page` — [mcp/resources/man.py:45](https://github.com/basicmachines-co/basic-memory/blob/9b47a7cd4784ca3a4df5d85437bdbd2db2dee587/src/basic_memory/mcp/resources/man.py#L45) - Description (verbatim): One manual page, e.g. memory://man/search-notes(3). Section-3 pages document each MCP tool with parameters, verified examples, and gotchas. Any common spelling of the page name resolves: search-notes(3), 3/search-notes, search_notes. - `memory://{project}/{path*}` — name: `note` — [mcp/resources/notes.py:133](https://github.com/basicmachines-co/basic-memory/blob/9b47a7cd4784ca3a4df5d85437bdbd2db2dee587/src/basic_memory/mcp/resources/notes.py#L133) - Description (verbatim): A note's raw markdown, addressed by its memory:// URL — memory://<project>/<identifier>, e.g. memory://research/specs/search-design. The identifier may be a permalink, a title, or a file path in the project. - `memory://{workspace}/{project}/info` — name: `None` — [mcp/resources/project_info.py:19](https://github.com/basicmachines-co/basic-memory/blob/9b47a7cd4784ca3a4df5d85437bdbd2db2dee587/src/basic_memory/mcp/resources/project_info.py#L19) - Description (verbatim): Get information and statistics about a Basic Memory workspace project. | G33: Markdown (text/markdown)
A34: basic-memory | B34: Prompts | C34: Yes | E34: 4: continue_conversation, getting_started, recent_activity, search_knowledge_base | F34: ## 4. Prompts - `continue_conversation` — [mcp/prompts/continue_conversation.py:22](https://github.com/basicmachines-co/basic-memory/blob/9b47a7cd4784ca3a4df5d85437bdbd2db2dee587/src/basic_memory/mcp/prompts/continue_conversation.py#L22) - Description (verbatim): Continue a previous conversation - Arguments: `topic`, `timeframe` - `getting_started` — [mcp/prompts/getting_started.py:166](https://github.com/basicmachines-co/basic-memory/blob/9b47a7cd4784ca3a4df5d85437bdbd2db2dee587/src/basic_memory/mcp/prompts/getting_started.py#L166) - Description (verbatim): Introduce Basic Memory and help the user create their first note - Arguments: `project` - `recent_activity` — [mcp/prompts/recent_activity.py:23](https://github.com/basicmachines-co/basic-memory/blob/9b47a7cd4784ca3a4df5d85437bdbd2db2dee587/src/basic_memory/mcp/prompts/recent_activity.py#L23) - Description (verbatim): Get recent activity from one project: the given one, else the default project. Lists every project only when no default is set - Arguments: `timeframe`, `project` - `search_knowledge_base` — [mcp/prompts/search.py:20](https://github.com/basicmachines-co/basic-memory/blob/9b47a7cd4784ca3a4df5d85437bdbd2db2dee587/src/basic_memory/mcp/prompts/search.py#L20) - Description (verbatim): Search across all content in basic-memory - Arguments: `query`, `timeframe` | G34: A hint text for the AI
A35: basic-memory | B35: Logging | C35: Partially | E35: Only in project management tools: context.info("Listing all available projects"), "Creating project: ...", "Deleting project: ..." sent as MCP log notifications | J35: mcp/tools/project_management.py:389, 616, 848
A36: basic-memory | B36: Sampling | C36: No
A37: basic-memory | B37: Roots | C37: No
A38: basic-memory | B38: Authorization | C38: Yes | E38: Local (stdio): none (access = file access). Cloud: OAuth browser sign-in via WorkOS AuthKit, subscription checked at sign-in. The local server can call the cloud with an API key or an OAuth token (key takes precedence). DCR / metadata not documented. | H38: Several methods | I38: WorkOS AuthKit (cloud) | J38: cloud-guide; README:147; mcp/tools/utils.py:229
A39: basic-memory | B39: Elicitation | C39: No | E39: Not found; instead the instructions ask the AI to offer and "wait for them to agree before writing anything" | J39: server.py:243-275
A40: basic-memory | B40: Tasks | C40: No | E40: Not found; cloud project deletion runs asynchronously in the background, but not via MCP Tasks | J40: cloud-guide
A41: basic-memory | B41: Configuration | C41: Yes | E41: ~/.basic-memory/config.json and environment variables: default_project, enable_posix_tools (on), enable_project_delete (off), write_note_overwrite_default (off) etc.; tool-group visibility via FastMCP tags at startup | J41: server.py:36-52, 125-129; config_models.py:196, 591-618
A42: basic-memory | B42: Error Reporting | C42: Yes | E42: Refusal system: isError: true + code NOT_FOUND, AMBIGUOUS, ALREADY_EXISTS, REVISION_CONFLICT, INVALID_ARGUMENTS, OUTSIDE_PROJECT, LOCKED, UNSUPPORTED, PARTIAL_FAILURE, OUTCOME_UNKNOWN, UNAVAILABLE + "Try instead: ..." | G42: Text "CODE: message\nTry instead: ..." or JSON {"error","message","try_instead"} | J42: mcp/refusals.py:1-80
A43: basic-memory | B43: Subscription | C43: No
A44: basic-memory | B44: Progress Tracking | C44: No
A45: basic-memory | B45: Cancellation | C45: No
A46: basic-memory | B46: Other | C46: Yes | E46: Client dependency: middleware remembers the client name; search/fetch (for ChatGPT) work only for the OpenAI client, others get "Use search_notes instead" | J46: mcp/client_info.py; mcp/tools/chatgpt_tools.py:28-38, 172-174
A47: shapes | B47: Tools | C47: Yes | E47: 35 tools, "All tools are read-only - no data is modified through the MCP server": employees 8, performance reviews 7, time off 8, surveys 4, attendance 2, working time policies 1, knowledge base 2, helpdesk 3; aggregate_* tools compute statistics | F47: Not published verbatim; only the tool names are known | G47: Not documented; lists of records and aggregates ("counts, percentages, and distributions") | J47: https://mcp.shapes.co/
A48: shapes | B48: Resources | C48: Unknown | E48: Not documented; the only OAuth scope mcp:tools indirectly suggests tools only | J48: https://mcp.shapes.co/.well-known/oauth-protected-resource
A49: shapes | B49: Prompts | C49: Unknown | E49: The page mentions "built-in skills"; implementation not stated | J49: https://mcp.shapes.co/
A50: shapes | B50: Logging | C50: Unknown
A51: shapes | B51: Sampling | C51: Unknown
A52: shapes | B52: Roots | C52: Unknown
A53: shapes | B53: Authorization | C53: Yes | E53: OAuth 2.0 + PKCE; metadata documents published; Dynamic Client Registration (registration_endpoint https://mcp.shapes.co/register); grant types authorization_code, refresh_token; PKCE S256; only scope mcp:tools | H53: Dynamic Client Registration | I53: https://mcp.shapes.co (sign-in with a Shapes account) | J53: https://mcp.shapes.co/.well-known/oauth-protected-resource; https://mcp.shapes.co/.well-known/oauth-authorization-server
A54: shapes | B54: Elicitation | C54: Unknown
A55: shapes | B55: Tasks | C55: Unknown
A56: shapes | B56: Configuration | C56: No | E56: No user settings ("No API keys required") | J56: https://mcp.shapes.co/
A57: shapes | B57: Error Reporting | C57: Unknown
A58: shapes | B58: Subscription | C58: Unknown
A59: shapes | B59: Progress Tracking | C59: Unknown
A60: shapes | B60: Cancellation | C60: Unknown
A61: shapes | B61: Other | C61: Unknown
A62: lucid | B62: Tools | C62: Yes | E62: 30-35 tools according to third-party catalogues (combined 40 names): reading, creating, editing, deleting shapes, sharing, comments, export, running JavaScript in a document (lucid_run_script, Scalekit only). Annotations not published. Separate read-only endpoint. | F62: Not published verbatim; short paraphrases in Composio and Scalekit | G62: Not documented. Scalekit: search returns up to 200 results; fetch returns structured content (pages, blocks, lines); export_document_as_png returns a PNG image | J62: https://composio.dev/toolkits/lucid_mcp/framework/hermes-agent.md; https://www.scalekit.com/connectors/lucidmcp
A63: lucid | B63: Resources | C63: Yes | E63: Probably: the skill says "Read any required lucid://... resource before calling a tool that requires it"; tool get_mcp_resource reads a resource by URI (e.g. diagram specifications) | J63: skills/lucid/SKILL.md; Composio
A64: lucid | B64: Prompts | C64: Unknown | E64: Not documented; Lucid distributes skills (client instructions outside the server) instead
A65: lucid | B65: Logging | C65: Unknown
A66: lucid | B66: Sampling | C66: Unknown
A67: lucid | B67: Roots | C67: Unknown
A68: lucid | B68: Authorization | C68: Yes | E68: OAuth 2.0 with Dynamic Client Registration; the user confirms access on first connection. Alternative for Team/Enterprise: API key without confirmation prompts. OAuth metadata could not be checked (robots.txt). | H68: Several methods | I68: Lucid | J68: README; Help Center
A69: lucid | B69: Elicitation | C69: Unknown
A70: lucid | B70: Tasks | C70: Unknown
A71: lucid | B71: Configuration | C71: Partially | E71: Choice of endpoint (full / readonly / repositories); enabled/disabled by the administrator | J71: Help Center
A72: lucid | B72: Error Reporting | C72: Unknown
A73: lucid | B73: Subscription | C73: Unknown
A74: lucid | B74: Progress Tracking | C74: Unknown
A75: lucid | B75: Cancellation | C75: Unknown
A76: lucid | B76: Other | C76: Yes | E76: MCP Apps: lucid_create_embed and lucid_create_embed_session_token - "internal tool for the MCP Apps extension" (embedding an interactive Lucid document in the AI client window) | J76: Composio; Scalekit
A77: gocardless | B77: Tools | C77: Yes | E77: 24 tools according to Composio: 16 reading, 7 writing, 1 feedback; required scope given for each writing tool (payments:write, refunds:write, mandates:write, subscriptions:write, payment_links:write) | F77: Not published verbatim | G77: Not documented; sensitive fields masked before the AI sees them (e-mail, phone, postcode, ID numbers); bank details never passed | J77: Composio; Support article
A78: gocardless | B78: Resources | C78: Unknown | E78: Not documented; the tool "Read gocardless resource" returns documentation, guides and code examples (resource function implemented as a tool) | J78: Composio
A79: gocardless | B79: Prompts | C79: Unknown | E79: Not documented; the tool "Integrate with gocardless" gives an overview of integration options | J79: Composio
A80: gocardless | B80: Logging | C80: Unknown | E80: Not documented as MCP logging; product-side event log (see D)
A81: gocardless | B81: Sampling | C81: Unknown
A82: gocardless | B82: Roots | C82: Unknown
A83: gocardless | B83: Authorization | C83: Yes | E83: Browser sign-in; OAuth metadata documents published; Dynamic Client Registration (registration_endpoint https://mcp.gocardless.com/register); grant_types authorization_code; PKCE S256; token_endpoint_auth_methods none (public clients); scopes_supported not given. Revocation: Settings -> Connected apps -> Revoke access. | H83: Dynamic Client Registration | I83: https://mcp.gocardless.com | J83: https://mcp.gocardless.com/.well-known/oauth-protected-resource; https://mcp.gocardless.com/.well-known/oauth-authorization-server; Support article
A84: gocardless | B84: Elicitation | C84: Yes | E84: Confirmation exists, mechanism not specified: "Higher-risk write actions, such as creating a payment, show a preview and wait for explicit confirmation before proceeding"; "read the confirmation preview before approving". Whether MCP Elicitation, a two-step tool or client confirmation is used is not stated. | G84: Preview of the action (content not documented) | J84: Support article; Developer docs
A85: gocardless | B85: Tasks | C85: Unknown
A86: gocardless | B86: Configuration | C86: Partially | E86: Choice of environment (Live/Sandbox) and set of rights at sign-in | J86: Developer docs; Support article
A87: gocardless | B87: Error Reporting | C87: Unknown
A88: gocardless | B88: Subscription | C88: Unknown
A89: gocardless | B89: Progress Tracking | C89: Unknown
A90: gocardless | B90: Cancellation | C90: Unknown
A91: gocardless | B91: Other | C91: Yes | E91: "Get environment" reports Sandbox or Live and how to switch; "Submit feedback" - session rating 1 to 5 | J91: Composio
A92: airwallex | B92: Tools | C92: Yes | E92: Exact list not published. According to scopes - reading: balances, contacts/beneficiaries, conversions, global accounts, cardholders, cards, card transactions, pa_view, payment links, account details, transfers, billing (9 objects), expenses, vendor bills, vendors; writing: contacts, cardholders, cards, payment links, billing (7 objects), feedback; plus documentation search. | F92: Not published; "The server annotates write tools (create, update, or delete) so clients can prompt for confirmation" | G92: Not documented | J92: https://mcp.airwallex.com/.well-known/oauth-protected-resource/mcp; agentos.md
A93: airwallex | B93: Resources | C93: Unknown | E93: Not documented; external skills instead of prompts
A94: airwallex | B94: Prompts | C94: Unknown | E94: Not documented; external skills instead
A95: airwallex | B95: Logging | C95: Unknown
A96: airwallex | B96: Sampling | C96: Unknown
A97: airwallex | B97: Roots | C97: Unknown
A98: airwallex | B98: Authorization | C98: Yes | E98: OAuth to the production account; metadata documents published; Dynamic Client Registration (registration_endpoint https://mcp.airwallex.com/mcp/register); grant types authorization_code, refresh_token; PKCE S256; client auth client_secret_post, client_secret_basic, private_key_jwt, none; 35 scopes (23 r:, 12 w:). Tokens refreshed automatically; a persistent 401 means the grant was revoked. | H98: Dynamic Client Registration | I98: https://mcp.airwallex.com/mcp | J98: https://mcp.airwallex.com/.well-known/oauth-protected-resource/mcp; https://mcp.airwallex.com/.well-known/oauth-authorization-server/mcp; skills/awx-best-practices/SKILL.md
A99: airwallex | B99: Elicitation | C99: Unknown
A100: airwallex | B100: Tasks | C100: Unknown
...

Sheet Actions
A1: Server | B1: # | C1: Tool (name in MCP) | D1: Meaningful action description | E1: Action type | F1: Enabled by default? | G1: Parameters (name: type; number of categories if enum) | H1: Number of parameters | I1: Source
A2: tavily | B2: 1 | C2: tavily_search | D2: Search the internet | E2: Read | F2: Yes | G2: query (string, req.); search_depth (enum, 4: basic/advanced/fast/ultra-fast); topic (enum, 2: general/news); time_range (enum, 4: day/week/month/year); start_date, end_date (string YYYY-MM-DD); max_results (number 5-20); include_images, include_image_descriptions, include_raw_content, include_favicon, exact_match (boolean); include_domains, exclude_domains (array of string); country (string) | H2: 15 | I2: src/index.ts:158-531
A3: tavily | B3: 2 | C3: tavily_extract | D3: Extract the content of web pages | E3: Read | F3: Yes | G3: urls (array, req.); extract_depth (enum, 2); include_images, include_favicon (boolean); format (enum, 2: markdown/text); query (string) | H3: 6 | I3: src/index.ts:158-531
A4: tavily | B4: 3 | C4: tavily_crawl | D4: Crawl a website | E4: Read | F4: Yes | G4: url (req.); max_depth, max_breadth, limit (integer >= 1); instructions (string); select_paths, select_domains (array of regex); allow_external (boolean); extract_depth (enum, 2); format (enum, 2); include_favicon (boolean) | H4: 11 | I4: src/index.ts:158-531
A5: tavily | B5: 4 | C5: tavily_map | D5: Build a site map | E5: Read | F5: Yes | G5: url (req.); max_depth, max_breadth, limit (integer); instructions (string); select_paths, select_domains (array); allow_external (boolean) | H5: 8 | I5: src/index.ts:158-531
A6: tavily | B6: 5 | C6: tavily_research | D6: Research a topic (multi-step research by Tavily's agent) | E6: Read | F6: Yes | G6: input (string, req.); model (enum, 3: mini/pro/auto) | H6: 2 | I6: src/index.ts:158-531
A7: tavily | B7: 6 | C7: tavily_feedback | D7: Send Tavily a rating of the search results, including the agent's final answer to the user | E7: Write | F7: Unknown | G7: session_id / request_id (string, at least one); agent_score, human_score (number|string); extra_scores (array of {label, value}); comment, response_delivered (string); used_urls, used_ids, used_citations (array of string); urls_scores (array of {id, url, agent_score, scores, comment}) | H7: 11 | I7: src/index.ts:431-531 (local code only; not in the remote server documentation)
A8: grafana | B8: 1 | C8: list_teams | D8: Search for Grafana teams by a query string. | E8: Read | F8: No | G8: query: string | H8: 1 | I8: https://github.com/grafana/mcp-grafana/blob/e97cd4479eb40d25bc8d466db1651c29ce0c783e/tools/admin.go#L36
A9: grafana | B9: 2 | C9: list_users_by_org | D9: List users in the Grafana organization, optionally filtered by a search query. | E9: Read | F9: No | G9: query: string; limit: int; page: int | H9: 3 | I9: https://github.com/grafana/mcp-grafana/blob/e97cd4479eb40d25bc8d466db1651c29ce0c783e/tools/admin.go#L103
A10: grafana | B10: 3 | C10: list_all_roles | D10: List all roles in Grafana. | E10: Read | F10: No | G10: delegatableOnly: bool | H10: 1 | I10: https://github.com/grafana/mcp-grafana/blob/e97cd4479eb40d25bc8d466db1651c29ce0c783e/tools/admin.go#L135
A11: grafana | B11: 4 | C11: get_role_details | D11: Get detailed information about a specific Grafana role by its UID, including permissions, metadata, and configuration. | E11: Read | F11: No | G11: roleUID: string (req.) | H11: 1 | I11: https://github.com/grafana/mcp-grafana/blob/e97cd4479eb40d25bc8d466db1651c29ce0c783e/tools/admin.go#L162
A12: grafana | B12: 5 | C12: get_role_assignments | D12: List all assignments for a specific role, showing which users, teams, and service accounts have been assigned this role. | E12: Read | F12: No | G12: roleUID: string (req.) | H12: 1 | I12: https://github.com/grafana/mcp-grafana/blob/e97cd4479eb40d25bc8d466db1651c29ce0c783e/tools/admin.go#L189
A13: grafana | B13: 6 | C13: list_user_roles | D13: List all roles assigned to one or more users. | E13: Read | F13: No | G13: userIds: []int64 (req.) | H13: 1 | I13: https://github.com/grafana/mcp-grafana/blob/e97cd4479eb40d25bc8d466db1651c29ce0c783e/tools/admin.go#L217
... A114: grafana | B114: 107 | C114: delete_snapshot | D114: Delete a Grafana snapshot by snapshot key. | E114: Write | F114: Yes | G114: key: string (req.) | H114: 1 | I114: https://github.com/grafana/mcp-grafana/blob/e97cd4479eb40d25bc8d466db1651c29ce0c783e/tools/snapshot.go#L262
A115: grafana | B115: 108 | C115: query_sql | D115: Query a supported SQL datasource (ClickHouse, Snowflake, Athena, MySQL, PostgreSQL, MSSQL) via Grafana. | E115: Write | F115: No | G115: not parsed (embedded struct QuerySQLParams) | H115: Unknown | I115: https://github.com/grafana/mcp-grafana/blob/e97cd4479eb40d25bc8d466db1651c29ce0c783e/tools/sql_tools.go#L265
A116: grafana | B116: 109 | C116: list_sql_databases | D116: List databases, schemas, or catalogs from a supported SQL datasource. | E116: Read | F116: No | G116: not parsed (embedded struct ListSQLDatabasesParams) | H116: Unknown | I116: https://github.com/grafana/mcp-grafana/blob/e97cd4479eb40d25bc8d466db1651c29ce0c783e/tools/sql_tools.go#L283
A117: grafana | B117: 110 | C117: list_sql_tables | D117: List tables from a supported SQL datasource (ClickHouse, Snowflake, Athena, MySQL, PostgreSQL, MSSQL). | E117: Read | F117: No | G117: not parsed (embedded struct ListSQLTablesParams) | H117: Unknown | I117: https://github.com/grafana/mcp-grafana/blob/e97cd4479eb40d25bc8d466db1651c29ce0c783e/tools/sql_tools.go#L295
A118: grafana | B118: 111 | C118: describe_sql_table | D118: Get column schema for a table in a supported SQL datasource (ClickHouse, Snowflake, Athena, MySQL, PostgreSQL, MSSQL). | E118: Read | F118: No | G118: not parsed (embedded struct DescribeSQLTableParams) | H118: Unknown | I118: https://github.com/grafana/mcp-grafana/blob/e97cd4479eb40d25bc8d466db1651c29ce0c783e/tools/sql_tools.go#L307
A119: grafana | B119: 112 | C119: search_tempo_traces | D119: Search for traces using TraceQL queries | E119: Read | F119: Yes | G119: datasourceUid: string (req.); query: string (req.); start: string; end: string | H119: 4 | I119: https://github.com/grafana/mcp-grafana/blob/e97cd4479eb40d25bc8d466db1651c29ce0c783e/tools/tempo.go#L699
A120: grafana | B120: 113 | C120: query_tempo_metrics | D120: Compute trace-derived metrics using a TraceQL metrics query. | E120: Read | F120: Yes | G120: datasourceUid: string (req.); query: string (req.); type: string, enum 2; start: string; end: string | H120: 5 | I120: https://github.com/grafana/mcp-grafana/blob/e97cd4479eb40d25bc8d466db1651c29ce0c783e/tools/tempo.go#L711
A121: grafana | B121: 114 | C121: get_tempo_trace | D121: Retrieve a specific trace by ID | E121: Read | F121: Yes | G121: focus_span_id: *string; datasourceUid: string (req.); trace_id: string (req.) | H121: 3 | I121: https://github.com/grafana/mcp-grafana/blob/e97cd4479eb40d25bc8d466db1651c29ce0c783e/tools/tempo.go#L723
A122: grafana | B122: 115 | C122: diff_tempo_traces | D122: Compare two complete traces. | E122: Read | F122: Yes | G122: datasourceUid: string (req.); base_trace_id: string (req.); compare_trace_id: string (req.); base_start: string; base_end: string; compare_start: string; compare_end: string; format: string, enum 3 | H122: 8 | I122: https://github.com/grafana/mcp-grafana/blob/e97cd4479eb40d25bc8d466db1651c29ce0c783e/tools/tempo.go#L736
A123: grafana | B123: 116 | C123: list_tempo_attribute_names | D123: List available attribute names for TraceQL queries. | E123: Read | F123: Yes | G123: datasourceUid: string (req.); scope: string | H123: 2 | I123: https://github.com/grafana/mcp-grafana/blob/e97cd4479eb40d25bc8d466db1651c29ce0c783e/tools/tempo.go#L748
A124: grafana | B124: 117 | C124: list_tempo_attribute_values | D124: List values for a fully scoped attribute name (e.g. resource.service.name). | E124: Read | F124: Yes | G124: datasourceUid: string (req.); name: string (req.); filter-query: string | H124: 3 | I124: https://github.com/grafana/mcp-grafana/blob/e97cd4479eb40d25bc8d466db1651c29ce0c783e/tools/tempo.go#L760
A125: grafana | B125: 118 | C125: get_tempo_traceql_docs | D125: Retrieve TraceQL reference documentation with examples, covering attribute filters, aggregates, structural operators, and metrics queries. | E125: Read | F125: Yes | G125: topic: string, enum 4 (req.) | H125: 1 | I125: https://github.com/grafana/mcp-grafana/blob/e97cd4479eb40d25bc8d466db1651c29ce0c783e/tools/tempo.go#L772
A126: grafana | B126: 119 | C126: user_info | D126: Get information about the current Grafana identity: login, email, name, whether it is a Grafana (server) admin, the current organization, and the organizations it can access (with roles). | E126: Read | F126: Yes | G126: none | H126: 0 | I126: https://github.com/grafana/mcp-grafana/blob/e97cd4479eb40d25bc8d466db1651c29ce0c783e/tools/user.go#L45
A127: basic-memory | B127: 1 | C127: basic_memory_diagnostics | D127: Return version, system, and configuration diagnostics for Basic Memory. | E127: Read | F127: Yes | G127: none | H127: 0 | I127: https://github.com/basicmachines-co/basic-memory/blob/9b47a7cd4784ca3a4df5d85437bdbd2db2dee587/src/basic_memory/mcp/tools/basic_memory_diagnostics.py#L34
A128: basic-memory | B128: 2 | C128: build_context | D128: Build context from a memory:// URI to continue conversations naturally. | E128: Read | F128: Yes | G128: url: MemoryUrl (req.); project: Optional[str]; project_id: Optional[str]; depth: str; timeframe: Optional[TimeFrame]; page: int; page_size: int; max_related: int; output_format: Literal['json', 'text']; compact: bool | H128: 10 | I128: https://github.com/basicmachines-co/basic-memory/blob/9b47a7cd4784ca3a4df5d85437bdbd2db2dee587/src/basic_memory/mcp/tools/build_context.py#L213
A129: basic-memory | B129: 3 | C129: search | D129: OpenAI/ChatGPT connector search adapter (works only for the OpenAI client; others get "Use search_notes instead") | E129: Read | F129: Yes | G129: query: str (req.) | H129: 1 | I129: https://github.com/basicmachines-co/basic-memory/blob/9b47a7cd4784ca3a4df5d85437bdbd2db2dee587/src/basic_memory/mcp/tools/chatgpt_tools.py#L158
A130: basic-memory | B130: 4 | C130: fetch | D130: OpenAI/ChatGPT connector fetch adapter (works only for the OpenAI client) | E130: Read | F130: Yes | G130: id: str (req.) | H130: 1 | I130: https://github.com/basicmachines-co/basic-memory/blob/9b47a7cd4784ca3a4df5d85437bdbd2db2dee587/src/basic_memory/mcp/tools/chatgpt_tools.py#L248
... A167: basic-memory | B167: 41 | C167: write_note | D167: Create a markdown note. | E167: Write | F167: Yes | G167: title: str (req.); content: str (req.); directory: str (req.); project: Optional[str]; workspace: Optional[str]; project_id: Optional[str]; tags: list[str]; note_type: str; metadata: dict[str, Any]; overwrite: bool; expected_checksum: str; output_format: Literal['text', 'json'] | H167: 12 | I167: https://github.com/basicmachines-co/basic-memory/blob/9b47a7cd4784ca3a4df5d85437bdbd2db2dee587/src/basic_memory/mcp/tools/write_note.py#L106
A168: shapes | B168: 1 | C168: list_employees | D168: List employees | E168: Read | F168: Yes | G168: Not published | H168: Unknown | I168: https://mcp.shapes.co/
A169: shapes | B169: 2 | C169: aggregate_employees | D169: Compute statistics about employees (counts, percentages, distributions) | E169: Read | F169: Yes | G169: Not published | H169: Unknown | I169: https://mcp.shapes.co/
A170: shapes | B170: 3 | C170: get_current_employee | D170: Get the signed-in employee's own record | E170: Read | F170: Yes | G170: Not published | H170: Unknown | I170: https://mcp.shapes.co/
A171: shapes | B171: 4 | C171: get_reporting_chain | D171: Get an employee's reporting chain | E171: Read | F171: Yes | G171: Not published | H171: Unknown | I171: https://mcp.shapes.co/
A172: shapes | B172: 5 | C172: list_entities | D172: List company entities | E172: Read | F172: Yes | G172: Not published | H172: Unknown | I172: https://mcp.shapes.co/
A173: shapes | B173: 6 | C173: list_employee_field_types | D173: List employee profile field types | E173: Read | F173: Yes | G173: Not published | H173: Unknown | I173: https://mcp.shapes.co/
A174: shapes | B174: 7 | C174: list_employee_field_value_changes | D174: List the history of changes to employee field values | E174: Read | F174: Yes | G174: Not published | H174: Unknown | I174: https://mcp.shapes.co/
A175: shapes | B175: 8 | C175: list_profile_pictures | D175: List employee profile pictures | E175: Read | F175: Yes | G175: Not published | H175: Unknown | I175: https://mcp.shapes.co/
A176: shapes | B176: 9 | C176: list_performance_review_cycles | D176: List performance review cycles | E176: Read | F176: Yes | G176: Not published | H176: Unknown | I176: https://mcp.shapes.co/
A177: shapes | B177: 10 | C177: list_performance_review_participations | D177: List participations in performance reviews | E177: Read | F177: Yes | G177: Not published | H177: Unknown | I177: https://mcp.shapes.co/
A178: shapes | B178: 11 | C178: list_performance_review_reviewers | D178: List reviewers of performance reviews | E178: Read | F178: Yes | G178: Not published | H178: Unknown | I178: https://mcp.shapes.co/
A179: shapes | B179: 12 | C179: list_my_performance_review_participations | D179: List the user's own performance review participations | E179: Read | F179: Yes | G179: Not published | H179: Unknown | I179: https://mcp.shapes.co/
... A514: calendly | B514: 36 | C514: load_calendly_skill | D514: Load a server-side skill (instructions for the agent; no REST equivalent) | E514: Read | F514: Unknown | G514: Not published | H514: Unknown | I514: https://developer.calendly.com/docs/mcp/supported-tools
A515: context7 | B515: 1 | C515: resolve-library-id | D515: Find a library and its Context7 ID | E515: Read | F515: Yes | G515: query: string (req.); libraryName: string (req.) | H515: 2 | I515: https://github.com/upstash/context7/blob/b5e81de845092694ba1bfc5af15400f319c89b6d/packages/mcp/src/index.ts#L306-L438
A516: context7 | B516: 2 | C516: query-docs | D516: Get up-to-date documentation snippets for a library | E516: Read | F516: Yes | G516: libraryId: string (req., format /org/project[/version]); query: string (req.); language: string | H516: 3 | I516: https://github.com/upstash/context7/blob/b5e81de845092694ba1bfc5af15400f319c89b6d/packages/mcp/src/index.ts#L306-L438
A517: heroku | B517: 1 | C517: list_addons | D517: List add-ons: all apps or specific app, detailed metadata | E517: Read | F517: Yes | G517: all: boolean; app: string | H517: 2 | I517: https://github.com/heroku/heroku-mcp-server/blob/4afcbe1a042b78e81385280ac5adaeb0000dba6e/src/tools/addons.ts#L36
A518: heroku | B518: 2 | C518: get_addon_info | D518: Get add-on details: plan, state, billing | E518: Read | F518: Yes | G518: addon: string (req.); app: string | H518: 2 | I518: https://github.com/heroku/heroku-mcp-server/blob/4afcbe1a042b78e81385280ac5adaeb0000dba6e/src/tools/addons.ts#L77
A519: heroku | B519: 3 | C519: create_addon | D519: Create add-on: specify service, plan, custom names | E519: Write | F519: Yes | G519: app: string (req.); as: string; name: string; serviceAndPlan: string (req.) | H519: 4 | I519: https://github.com/heroku/heroku-mcp-server/blob/4afcbe1a042b78e81385280ac5adaeb0000dba6e/src/tools/addons.ts#L115
A520: heroku | B520: 4 | C520: list_addon_services | D520: List available add-on services and features | E520: Read | F520: Yes | G520: json: boolean | H520: 1 | I520: https://github.com/heroku/heroku-mcp-server/blob/4afcbe1a042b78e81385280ac5adaeb0000dba6e/src/tools/addons.ts#L157
A521: heroku | B521: 5 | C521: list_addon_plans | D521: List service plans: features, pricing, availability | E521: Read | F521: Yes | G521: service: string (req.); json: boolean | H521: 2 | I521: https://github.com/heroku/heroku-mcp-server/blob/4afcbe1a042b78e81385280ac5adaeb0000dba6e/src/tools/addons.ts#L194
A522: heroku | B522: 6 | C522: list_ai_available_models | D522: List available AI inference models (registered only if the @heroku/plugin-ai plugin is installed) | E522: Read | F522: No | G522: none | H522: 0 | I522: https://github.com/heroku/heroku-mcp-server/blob/4afcbe1a042b78e81385280ac5adaeb0000dba6e/src/tools/ai.ts#L19
A523: heroku | B523: 7 | C523: provision_ai_model | D523: Provision AI model access for app (registered only if the @heroku/plugin-ai plugin is installed) | E523: Write | F523: No | G523: app: string (req.); modelName: string (req.); as: string | H523: 3 | I523: https://github.com/heroku/heroku-mcp-server/blob/4afcbe1a042b78e81385280ac5adaeb0000dba6e/src/tools/ai.ts#L60
A524: heroku | B524: 8 | C524: make_ai_inference | D524: Make inference request to Heroku AI API (registered only if the @heroku/plugin-ai plugin is installed) | E524: Write | F524: No | G524: app: string (req.); modelResource: string (req.); json: boolean; output: string | H524: 4 | I524: https://github.com/heroku/heroku-mcp-server/blob/4afcbe1a042b78e81385280ac5adaeb0000dba6e/src/tools/ai.ts#L164
A525: heroku | B525: 9 | C525: list_apps | D525: List Heroku apps: owned, collaborator access, team/space filtering | E525: Read | F525: Yes | G525: all: boolean; personal: boolean; space: string; team: string | H525: 4 | I525: https://github.com/heroku/heroku-mcp-server/blob/4afcbe1a042b78e81385280ac5adaeb0000dba6e/src/tools/apps.ts#L32
A526: heroku | B526: 10 | C526: get_app_info | D526: Get app details: config, dynos, addons, access, domains | E526: Read | F526: Yes | G526: app: string (req.); json: boolean | H526: 2 | I526: https://github.com/heroku/heroku-mcp-server/blob/4afcbe1a042b78e81385280ac5adaeb0000dba6e/src/tools/apps.ts#L72
... A551: heroku | B551: 35 | C551: list_teams | D551: Lists accessible Heroku Teams. | E551: Read | F551: Yes | G551: json: boolean | H551: 1 | I551: https://github.com/heroku/heroku-mcp-server/blob/4afcbe1a042b78e81385280ac5adaeb0000dba6e/src/tools/teams.ts#L39
A552: heroku | B552: 36 | C552: deploy_one_off_dyno | D552: Run code/commands in a Heroku one-off dyno (paths validated: no .., no absolute paths, no shell metacharacters) | E552: Write | F552: Yes | G552: name: string, 5-30 chars (req.); command: string (req.); sources: array of {relativePath, contents}; further parameters see deploy-to-heroku.ts:680 | H552: Unknown | I552: https://github.com/heroku/heroku-mcp-server/blob/4afcbe1a042b78e81385280ac5adaeb0000dba6e/src/tools/deploy-to-heroku.ts#L749
A553: indeed | B553: 1 | C553: Job Search | D553: Search for jobs; returns titles, companies, locations, salaries and application links | E553: Read | F553: Yes | G553: title/keywords; location; employment type (exact schema not published) | H553: Unknown | I553: https://docs.indeed.com/mcp/
A554: indeed | B554: 2 | C554: Job Detail | D554: Get the details of a job | E554: Read | F554: Yes | G554: job ID (exact schema not published) | H554: Unknown | I554: https://docs.indeed.com/mcp/
A555: indeed | B555: 3 | C555: Get Resume | D555: Get the user's own resume (experience) from the Indeed profile (scope job_seeker.profile.read) | E555: Read | F555: Yes | G555: none documented | H555: 0 | I555: https://docs.indeed.com/mcp/
A556: indeed | B556: 4 | C556: Get Company Data | D556: Get company data: satisfaction, compensation, culture, management, reviews | E556: Read | F556: Yes | G556: company (exact schema not published) | H556: Unknown | I556: https://docs.indeed.com/mcp/
A557: launchdarkly | B557: 1 | C557: list-flags | D557: List feature flags | E557: Read | F557: Yes | G557: Not published | H557: Unknown | I557: https://mcp.launchdarkly.com/mcp/v1/install
A558: launchdarkly | B558: 2 | C558: get-flag | D558: Get a feature flag | E558: Read | F558: Yes | G558: Not published | H558: Unknown | I558: https://mcp.launchdarkly.com/mcp/v1/install
A559: launchdarkly | B559: 3 | C559: get-flag-health | D559: Get the health of a flag | E559: Read | F559: Yes | G559: Not published | H559: Unknown | I559: https://mcp.launchdarkly.com/mcp/v1/install
A560: launchdarkly | B560: 4 | C560: get-flag-status-across-envs | D560: Get a flag's status across environments | E560: Read | F560: Yes | G560: Not published | H560: Unknown | I560: https://mcp.launchdarkly.com/mcp/v1/install
A561: launchdarkly | B561: 5 | C561: find-stale-flags | D561: Find stale flags | E561: Read | F561: Yes | G561: Not published | H561: Unknown | I561: https://mcp.launchdarkly.com/mcp/v1/install
A562: launchdarkly | B562: 6 | C562: check-removal-readiness | D562: Check whether a flag can be removed (verdict safe / caution / blocked) | E562: Read | F562: Yes | G562: Not published | H562: Unknown | I562: https://mcp.launchdarkly.com/mcp/v1/install
A563: launchdarkly | B563: 7 | C563: create-flag | D563: Create a feature flag (starts OFF in all environments) | E563: Write | F563: Yes | G563: Not published | H563: Unknown | I563: https://mcp.launchdarkly.com/mcp/v1/install
A564: launchdarkly | B564: 8 | C564: toggle-flag | D564: Toggle a flag on/off (may require approval; marked Destructive on /mcp/v1) | E564: Write | F564: Yes | G564: Not published | H564: Unknown | I564: https://mcp.launchdarkly.com/mcp/v1/install
A565: launchdarkly | B565: 9 | C565: update-flag-settings | D565: Update flag settings | E565: Write | F565: Yes | G565: Not published | H565: Unknown | I565: https://mcp.launchdarkly.com/mcp/v1/install
A566: launchdarkly | B566: 10 | C566: update-rollout | D566: Update the rollout (marked Destructive on /mcp/v1) | E566: Write | F566: Yes | G566: Not published | H566: Unknown | I566: https://mcp.launchdarkly.com/mcp/v1/install
A567: launchdarkly | B567: 11 | C567: update-targeting-rules | D567: Update targeting rules (Destructive) | E567: Write | F567: Yes | G567: Not published | H567: Unknown | I567: https://mcp.launchdarkly.com/mcp/v1/install
... A619: similarweb | B619: 43 | C619: ASO Search Results | D619: ASO Search Results (consumes data credits) [Apps and ASO] | E619: Read | F619: Unknown | G619: Not published (domains, keywords, app IDs, countries, periods) | H619: Unknown | I619: https://docs.similarweb.com/api-v5/mcp-integration/mcp-setup

Sheet Observations
A1: Server (or "General") | B1: Observation type | C1: Observation | D1: Source / example
A2: tavily | B2: Systematic difference | C2: Vendor interests are built into the tool descriptions: tavily_feedback asks the agent to send Tavily ratings and its final answer to the user, so the agent works as a free data labeller for the vendor. | D2: src/index.ts:431-531
A3: tavily | B3: New design option | C3: Commercial offers inside tool responses: in keyless mode the agent is offered payment (x402) and bonus credits for answering questions. These texts arrive as an ordinary result, not as an error, so the agent may take them as an instruction. | D3: src/index.ts:1026-1050
A4: tavily | B4: New design option | C4: The operator can override the agent: DEFAULT_PARAMETERS replaces the parameters chosen by the AI, and the AI is not told about it. | D4: src/index.ts:727-732
A5: tavily | B5: Systematic difference | C5: Open code != deployed service: the tool sets of the local version and of the remote endpoint differ. | D5: https://docs.tavily.com/documentation/mcp
A6: tavily | B6: Other | C6: Behavioural hints in the descriptions: "Use for news, facts, or data beyond your knowledge cutoff", "Use 'news' only when the user explicitly asks for news". | D6: 01b_tavily_pre_interaction_context.md
A7: grafana | B7: Systematic difference | C7: The most "governed" of the first three servers: many server-side mechanisms (read-only/query-free modes, classification of query languages by danger, enforced filters, a cost limiter, URL whitelists). | D7: README:505-656, 1404-1454
A8: grafana | B8: New design option | C8: A universal tool as a bypass of targeted restrictions: grafana_api_request ("Similar to 'gh api'") makes the other 118 tools convenient shortcuts; restrictions of individual tools do not work while it is enabled. | D8: tools/api.go:208-261
A9: grafana | B9: Systematic difference | C9: Responsibility is split: the server declares the required permissions (_meta), Grafana checks them. Security depends on how narrowly the administrator configured the token. | D9: permissions.go:9-41
A10: grafana | B10: New design option | C10: The server description for the AI depends on the configuration (dynamic instructions), so the same model sees a different "world" with different clients. | D10: cmd/mcp-grafana/main.go:112-122, 532-575
A11: grafana | B11: Systematic difference | C11: Context size as a design problem: about 27,000 tokens by default; the server addresses it with categories and economical tools. | D11: README:238-239
A12: grafana | B12: Other | C12: Commercial model of the cloud version: every connected user counts as a paid "active AI user". | D12: https://grafana.com/docs/grafana-cloud/platform/pricing-and-usage/assistant/
... A91: similarweb | B91: Other | C91: Divergence between marketing and the tool set (Amazon, lead enrichment). | D91: landing page vs setup page
